Workbook
Name _T01: #REF!

Sheet Chart
D2: CHART OF ACCOUNT
C4: Seg 1 | D4: Seg 2 | E4: Seg 3 | F4: Seg 4 | G4: Seg 5 | H4: Seg 6 | I4: Seg 7 | J4: Seg 8 | K4: Seg 9 | L4: Seg 10
C5: xx | D5: xxx.xx.xx | E5: xx.xxx | F5: x.xx | G5: xx.xx.xx | H5: xx.xx | I5: x.xx.xx | J5: xx | K5: xx | L5: xxxx
C14: LEGAL_ENITY | D14: ACCOUNT | E14: SUB_ACCOUNT | F14: COST CENTER | G14: BUSINESS_LINE | H14: BRAND | I14: CHANNEL | J14: INTERCOMPANY | K14: SITE | L14: RESERVE
B16: Số ký tự | C16: 2 | D16: 7 | E16: 5 | F16: 3 | G16: 6 | H16: 4 | I16: 5 | J16: 2 | K16: 2 | L16: 4
C17: 17 | D17: 4131101 | E17: 00000 | F17: 000 | G17: 000000 | H17: 0000 | I17: 00000 | J17: 00 | K17: 00 | L17: 0000
C18: 17 | D18: 1289999 | E18: ZZZZZ | F18: ZZZ | G18: ZZZZZZ | H18: ZZZZ | I18: ZZZZZ | J18: ZZ | K18: ZZ | L18: ZZZZ
C19: =CONCATENATE(C17,"-",D17,"-",E17,"-",F17,"-",G17,"-",H17,"-",I17,"-",J17,"-",K17,"-",L17) -> 17-4131101-00000-000-000000-0000-00000-00-00-0000 | N19: COA_LEGAL_ENITY
C20: =CONCATENATE(C18,"-",D18,"-",E18,"-",F18,"-",G18,"-",H18,"-",I18,"-",J18,"-",K18,"-",L18) -> 17-1289999-ZZZZZ-ZZZ-ZZZZZZ-ZZZZ-ZZZZZ-ZZ-ZZ-ZZZZ | N20: COA_ACCOUNT
B21: Cộng | C21: =SUM(C16:L16) -> 40 | N21: COA_SUB_ACCOUNT
N22: COA_COST_CENTER
B23: Proposed Chart of Accounts | N23: COA_BUSINESSLINE
N24: COA_BRAND
C25: Legal Entity | D25: Account | E25: Sub-Account | F25: Cost center | G25: Business Line | H25: Brand | I25: Channel | J25: Intercompany | K25: Site | L25: Reserve | N25: COA_CHANNEL
N26: COA_INTER_CO
B27: Exp1: | C27: Basis salary | N27: COA_SITE
B28: Segment name | C28: Legal Entity | D28: Account | E28: Sub-Account | F28: Cost center | G28: Business Line | H28: Brand | I28: Channel | J28: Intercompany | K28: Reserve | L28: Reserve | N28: COA_RESERVE
B29: Code | C29: 11 | D29: 642101 | E29: 3101 | F29: 103 | G29: 000 | H29: 000 | I29: 000 | J29: 00 | K29: 000 | L29: 000
B30: Description | C30: PartnerCompany | D30: Employees cost | E30: Basis salary | F30: Financial Accounting | G30: Default | H30: Default | I30: Default | J30: Default | K30: Default | L30: Default
B31: GL account | C31: 11.642101.3101.103.000.000.000.00.000
B33: Exp2: | C33: Receivable intercompany (PartnerCompany-DTC)
B34: Segment name | C34: Legal Entity | D34: Account | E34: Sub-Account | F34: Cost center | G34: Business Line | H34: Brand | I34: Channel | J34: Intercompany | K34: Reserve | L34: Reserve
B35: Code | C35: 11 | D35: 131101 | E35: 0000 | F35: 000 | G35: 000 | H35: 000 | I35: 000 | J35: 12 | K35: 000 | L35: 000
B36: Description | C36: PartnerCompany | D36: Trade account receivable | E36: Default | F36: Default | G36: Default | H36: Default | I36: Default | J36: DTC | K36: Default | L36: Default
B37: GL account | C37: 11.131101.0000.000.000.000.000.12.000
B39: Exp3: | C39: Revenue
B40: Segment name | C40: Legal Entity | D40: Account | E40: Sub-Account | F40: Cost center | G40: Business Line | H40: Brand | I40: Channel | J40: Intercompany | K40: Reserve | L40: Reserve
B41: Code | C41: 11 | D41: 511101 | E41: 0000 | F41: 000 | G41: 101 | H41: 101 | I41: 101 | J41: 00 | K41: 000 | L41: 000
B42: Description | C42: PartnerCompany | D42: Revenue | E42: Default | F42: Default | G42: Cake & Ice dream | H42: Korean | I42: Shop in shop | J42: Default | K42: Default | L42: Default
B43: GL account | C43: 11.511101.0000.000.101.101.101.00.000 | G43: Kem
C47: Budget | G47: PR/PO (Encumbrance) | K47: AP Invoice (N Actual/C Encumbrance) | O47: FA Asset
O48: Asset cost
B49: Summary | C49: Account | D49: Cost center | E49: Sub | G49: Account | H49: Cost center | I49: Sub | K49: Account | L49: Cost center | M49: Sub | O49: Account | P49: Cost center | Q49: Sub
B50: Kinh doanh. CAPEX | C50: 241101 | D50: HCM-Bộ phận Kinh doanh trực tiếp | E50: S&M (tủ đông) | F50: 90000000 | G50: 241101 | H50: HCM-Bộ phận Kinh doanh trực tiếp | I50: S&M (tủ đông) | J50: 100000000 | K50: 241101 | L50: HCM-Bộ phận Kinh doanh trực tiếp | M50: S&M (tủ đông) | O50: 242101 | P50: 0000 | Q50: 0000
C51: 241101 | D51: HCM-Bộ phận Kinh doanh trực tiếp | E51: LOG (xe tải, thiết bị máy móc…) | F51: 50000000 | G51: 241101 | H51: HCM-Bộ phận Kinh doanh trực tiếp | I51: LOG (xe tải, thiết bị máy móc…) | J51: 50000000 | K51: 241101 | L51: HCM-Bộ phận Kinh doanh trực tiếp | M51: LOG (xe tải, thiết bị máy móc…) | O51: 211101 | P51: 0000 | Q51: 0000
O53: Depriciation
O54: Account | P54: Cost center | Q54: Sub
O55: 641xxx | P55: HCM-Bộ phận logistic | Q55: Khấu hao/Máy móc, thiết bị
O56: 641xxx | P56: HCM-Bộ phận logistic | Q56: Khấu hao/Phương tiện vận tải

Sheet Seg 1_Công ty
A1: Segment 1 : xx (Công ty - Company)
A3: Mã | B3: Tên công ty | D3: Địa chỉ | E3: MST | F3: Tel | G3: Fax | H3: Ledger code | I3: OU code | J3: FA book | K3: Chủ tịch HĐQT | L3: KTT | M3: Tên kỳ
A4: 17 | M4: 01-2024

Sheet Seg 2_Account
A2: Segment 2 : xxx.xx.xx (Tài khoản - Account)
B4: Account code | F4: Account Name | G4: Level | H4: Parent | I4: BS Dr | J4: BS Cr | K4: ACCOUNT_TYPE | L4: THIRD_PARTY_CONTROL | M4: RECONCILE | N4: New
B5: =C5&D5&E5 -> 0000000 | C5: 000 | D5: 00 | E5: 00 | F5: Măc đinh | G5: 1
B6: =C6&D6&E6 -> 1110000 | C6: 111 | D6: 00 | E6: 00 | F6: Tiền Mặt | G6: 1 | H6: x | I6: BS111 | K6: Asset | M6: Y
B7: =C7&D7&E7 -> 1111000 | C7: 111 | D7: 10 | E7: 00 | F7: Tiền Mặt - VND | G7: 2 | H7: x | K7: Asset | M7: Y
B8: =C8&D8&E8 -> 1111101 | C8: 111 | D8: 11 | E8: 01 | F8: Tiền Mặt - VND | G8: 3 | K8: Asset | M8: Y
B9: =C9&D9&E9 -> 1112000 | C9: 111 | D9: 20 | E9: 00 | F9: Tiền mặt - Ngoại tệ | G9: 2 | H9: x | K9: Asset | M9: Y
B10: =C10&D10&E10 -> 1112101 | C10: 111 | D10: 21 | E10: 01 | F10: Tiền mặt - USD | G10: 3 | K10: Asset | M10: Y
B11: =C11&D11&E11 -> 1120000 | C11: 112 | D11: 00 | E11: 00 | F11: Tiền Gửi Ngân Hàng | G11: 1 | H11: x | I11: BS111 | K11: Asset | M11: Y
B12: =C12&D12&E12 -> 1121000 | C12: 112 | D12: 10 | E12: 00 | F12: Tiền gửi ngân hàng-VND | G12: 2 | H12: x | K12: Asset | M12: Y
B13: =C13&D13&E13 -> 1121101 | C13: 112 | D13: 11 | E13: 01 | F13: Tiền gửi ngân hàng-VND-VIETTINBANK | G13: 3 | K13: Asset | M13: Y
B14: =C14&D14&E14 -> 1121102 | C14: 112 | D14: 11 | E14: 02 | F14: Tiền gửi ngân hàng-VND-VIETCOMBANK | G14: 3 | K14: Asset | M14: Y
B15: =C15&D15&E15 -> 1122000 | C15: 112 | D15: 20 | E15: 00 | F15: Tiền gửi ngân hàng - Ngoại tệ | G15: 2 | H15: x | K15: Asset | M15: Y
B16: =C16&D16&E16 -> 1122101 | C16: 112 | D16: 21 | E16: 01 | F16: Tiền gửi ngân hàng-USD-VIETCOMBANK | G16: 3 | K16: Asset | M16: Y
B17: =C17&D17&E17 -> 1130000 | C17: 113 | D17: 00 | E17: 00 | F17: Tiền Đang Chuyển | G17: 1 | H17: x | I17: BS111 | K17: Asset
B18: =C18&D18&E18 -> 1131000 | C18: 113 | D18: 10 | E18: 00 | F18: Tiền đang chuyển-VND | G18: 2 | H18: x | K18: Asset
B19: =C19&D19&E19 -> 1131101 | C19: 113 | D19: 11 | E19: 01 | F19: Tiền đang chuyển giữa 2 tài khoản ngân hàng | G19: 3 | K19: Asset
B20: =C20&D20&E20 -> 1131102 | C20: 113 | D20: 11 | E20: 02 | F20: Tiền đang chuyển trong 1 tài khoản ngân hàng khi chưa đối soát | G20: 3 | K20: Asset
B21: =C21&D21&E21 -> 1132000 | C21: 113 | D21: 20 | E21: 00 | F21: Tiền đang chuyển-Ngoại tệ | G21: 2 | H21: x | K21: Asset
B22: =C22&D22&E22 -> 1132101 | C22: 113 | D22: 21 | E22: 01 | F22: Tiền đang chuyển-Ngoại tệ | G22: 3 | K22: Asset
B23: =C23&D23&E23 -> 1139000 | C23: 113 | D23: 90 | E23: 00 | F23: Trung gian tiền đang chuyển | G23: 2 | H23: x | K23: Asset
B24: =C24&D24&E24 -> 1139101 | C24: 113 | D24: 91 | E24: 01 | F24: Cash clearing | G24: 3 | K24: Asset
B25: =C25&D25&E25 -> 1210000 | C25: 121 | D25: 00 | E25: 00 | F25: Chứng khoán kinh doanh | G25: 1 | H25: x | I25: BS121 | K25: Asset
B26: =C26&D26&E26 -> 1211000 | C26: 121 | D26: 10 | E26: 00 | F26: Cổ phiếu | G26: 2 | H26: x | K26: Asset
B27: =C27&D27&E27 -> 1211101 | C27: 121 | D27: 11 | E27: 01 | F27: Cổ phiếu | G27: 3 | K27: Asset
B28: =C28&D28&E28 -> 1212000 | C28: 121 | D28: 20 | E28: 00 | F28: Trái phiếu | G28: 2 | H28: x | K28: Asset
B29: =C29&D29&E29 -> 1212101 | C29: 121 | D29: 21 | E29: 01 | F29: Trái phiếu | G29: 3 | K29: Asset
B30: =C30&D30&E30 -> 1218000 | C30: 121 | D30: 80 | E30: 00 | F30: Chứng khoán và công cụ tài chính khác | G30: 2 | H30: x | K30: Asset
B31: =C31&D31&E31 -> 1218101 | C31: 121 | D31: 81 | E31: 01 | F31: Chứng khoán và công cụ tài chính khác | G31: 3 | K31: Asset
B32: =C32&D32&E32 -> 1280000 | C32: 128 | D32: 00 | E32: 00 | F32: Đầu tư nắm giữ đến ngày đáo hạn | G32: 1 | H32: x | K32: Asset
B33: =C33&D33&E33 -> 1281000 | C33: 128 | D33: 10 | E33: 00 | F33: Tiền gửi có kỳ hạn | G33: 2 | H33: x | K33: Asset
B34: =C34&D34&E34 -> 1281101 | C34: 128 | D34: 11 | E34: 01 | F34: Tiền gửi có kỳ hạn dưới 3 tháng | G34: 3 | I34: BS112 | K34: Asset | L34: Supplier
B35: =C35&D35&E35 -> 1281102 | C35: 128 | D35: 11 | E35: 02 | F35: Tiền gửi có kỳ hạn trên 3 tháng đến 12 tháng | G35: 3 | I35: BS123 | K35: Asset | L35: Supplier
B36: =C36&D36&E36 -> 1283000 | C36: 128 | D36: 30 | E36: 00 | F36: Cho vay | G36: 2 | H36: x | I36: BS135 | K36: Asset
B37: =C37&D37&E37 -> 1283101 | C37: 128 | D37: 31 | E37: 01 | F37: Cho vay | G37: 3 | K37: Asset | L37: Supplier
B38: =C38&D38&E38 -> 1310000 | C38: 131 | D38: 00 | E38: 00 | F38: Phải thu khách hàng | G38: 1 | H38: x | K38: Asset
B39: =C39&D39&E39 -> 1311000 | C39: 131 | D39: 10 | E39: 00 | F39: Phải thu khách hàng | G39: 2 | H39: x | I39: BS131 | K39: Asset
B40: =C40&D40&E40 -> 1311101 | C40: 131 | D40: 11 | E40: 01 | F40: Phải thu khách hàng | G40: 3 | K40: Asset | L40: Customer
B41: =C41&D41&E41 -> 1312000 | C41: 131 | D41: 20 | E41: 00 | F41: Khách hàng trả tiền trước | G41: 2 | H41: x | J41: BS312
B42: =C42&D42&E42 -> 1312101 | C42: 131 | D42: 21 | E42: 01 | F42: Khách hàng trả tiền trước | G42: 3 | K42: Asset | L42: Customer
B43: =C43&D43&E43 -> 1319000 | C43: 131 | D43: 90 | E43: 00 | F43: Trung gian khoản phải thu | G43: 2 | H43: x | K43: Asset
B44: =C44&D44&E44 -> 1319101 | C44: 131 | D44: 91 | E44: 01 | F44: Phải thu chưa xác định đối tượng (Unidentifined) | G44: 3 | K44: Asset
B45: =C45&D45&E45 -> 1330000 | C45: 133 | D45: 00 | E45: 00 | F45: Thuế GTGT được khấu trừ HH, DV | G45: 1 | H45: x | I45: BS152 | K45: Asset
B46: =C46&D46&E46 -> 1331000 | C46: 133 | D46: 10 | E46: 00 | F46: Thuế GTGT được khấu trừ của hàng hóa, dịch vụ trong nước | G46: 2 | H46: x | K46: Asset
B47: =C47&D47&E47 -> 1331101 | C47: 133 | D47: 11 | E47: 01 | F47: Thuế GTGT được khấu trừ của hàng hóa, dịch vụ nhập khẩu | G47: 3 | K47: Asset
B48: =C48&D48&E48 -> 1332000 | C48: 133 | D48: 20 | E48: 00 | F48: Thuế GTGT được khấu trừ của hàng hóa, dịch vụ nhập khẩu | G48: 2 | H48: x | K48: Asset
B49: =C49&D49&E49 -> 1332101 | C49: 133 | D49: 21 | E49: 01 | F49: Thuế GTGT được khấu trừ của hàng hóa, dịch vụ nhập khẩu | G49: 3 | K49: Asset
B50: =C50&D50&E50 -> 1360000 | C50: 136 | D50: 00 | E50: 00 | F50: Phải thu nội bộ | G50: 1 | H50: x | I50: BS133 | K50: Asset
B51: =C51&D51&E51 -> 1361000 | C51: 136 | D51: 10 | E51: 00 | F51: Vốn kinh doanh ở các đơn vị trực thuộc | G51: 2 | H51: x | K51: Asset
B52: =C52&D52&E52 -> 1361101 | C52: 136 | D52: 11 | E52: 01 | F52: Vốn kinh doanh ở các đơn vị trực thuộc | G52: 3 | K52: Asset
B53: =C53&D53&E53 -> 1368000 | C53: 136 | D53: 80 | E53: 00 | F53: Phải thu nội bộ khác | G53: 2 | H53: x | K53: Asset
B54: =C54&D54&E54 -> 1368101 | C54: 136 | D54: 81 | E54: 01 | F54: Phải thu nội bộ khác | G54: 3 | K54: Asset
B55: =C55&D55&E55 -> 1380000 | C55: 138 | D55: 00 | E55: 00 | F55: Phải thu khác | G55: 1 | H55: x | K55: Asset
B56: =C56&D56&E56 -> 1381000 | C56: 138 | D56: 10 | E56: 00 | F56: Tài sản thiếu chờ xử lý | G56: 2 | H56: x | I56: BS139 | K56: Asset
B57: =C57&D57&E57 -> 1381101 | C57: 138 | D57: 11 | E57: 01 | F57: Tài sản thiếu chờ xử lý | G57: 3 | K57: Asset
B58: =C58&D58&E58 -> 1381102 | C58: 138 | D58: 11 | E58: 02 | F58: Trung gian đổi trả hàng | G58: 3 | K58: Asset | N58: Update 01/11/2024
B59: =C59&D59&E59 -> 1385000 | C59: 138 | D59: 50 | E59: 00 | F59: Phải thu về cổ phần hóa | G59: 2 | H59: x | I59: BS136 | K59: Asset
B60: =C60&D60&E60 -> 1385101 | C60: 138 | D60: 51 | E60: 01 | F60: Phải thu về cổ phần hóa | G60: 3 | K60: Asset
B61: =C61&D61&E61 -> 1388000 | C61: 138 | D61: 80 | E61: 00 | F61: Phải thu khác | G61: 2 | H61: x | I61: BS136 | K61: Asset
B62: =C62&D62&E62 -> 1388101 | C62: 138 | D62: 81 | E62: 01 | F62: Phải thu khác | G62: 3 | K62: Asset
B63: =C63&D63&E63 -> 1389000 | C63: 138 | D63: 90 | E63: 00 | F63: Trung gian cấn trừ | G63: 2 | H63: x | K63: Asset
B64: =C64&D64&E64 -> 1389101 | C64: 138 | D64: 91 | E64: 01 | F64: TK tiền ngân hàng trung gian cấn trừ | G64: 3 | K64: Asset
B65: =C65&D65&E65 -> 1410000 | C65: 141 | D65: 00 | E65: 00 | F65: Tạm ứng | G65: 1 | H65: x | K65: Asset
B66: =C66&D66&E66 -> 1411000 | C66: 141 | D66: 10 | E66: 00 | F66: Tạm ứng | G66: 2 | H66: x | I66: BS136 | K66: Asset
B67: =C67&D67&E67 -> 1411101 | C67: 141 | D67: 11 | E67: 01 | F67: Tạm ứng | G67: 3 | K67: Asset
B68: =C68&D68&E68 -> 1510000 | C68: 151 | D68: 00 | E68: 00 | F68: Hàng mua đang đi đường | G68: 1 | H68: x | I68: BS141 | K68: Asset
B69: =C69&D69&E69 -> 1511000 | C69: 151 | D69: 10 | E69: 00 | F69: Hàng mua đang đi đường | G69: 2 | H69: x | K69: Asset
B70: =C70&D70&E70 -> 1511101 | C70: 151 | D70: 11 | E70: 01 | F70: Hàng mua đang đi đường | G70: 3 | K70: Asset
B71: =C71&D71&E71 -> 1520000 | C71: 152 | D71: 00 | E71: 00 | F71: Nguyên liệu, vật liệu | G71: 1 | H71: x | I71: BS141 | K71: Asset
B72: =C72&D72&E72 -> 1521000 | C72: 152 | D72: 10 | E72: 00 | F72: Nguyên liệu, vật liệu | G72: 2 | H72: x | K72: Asset
B73: =C73&D73&E73 -> 1521101 | C73: 152 | D73: 11 | E73: 01 | F73: Nguyên liệu, vật liệu | G73: 3 | K73: Asset
B74: =C74&D74&E74 -> 1530000 | C74: 153 | D74: 00 | E74: 00 | F74: Công cụ, dụng cụ | G74: 1 | H74: x | I74: BS141 | K74: Asset
B75: =C75&D75&E75 -> 1531000 | C75: 153 | D75: 10 | E75: 00 | F75: Công cụ, dụng cụ | G75: 2 | H75: x | K75: Asset
B76: =C76&D76&E76 -> 1531101 | C76: 153 | D76: 11 | E76: 01 | F76: Công cụ, dụng cụ | G76: 3 | K76: Asset
B77: =C77&D77&E77 -> 1532000 | C77: 153 | D77: 20 | E77: 00 | F77: Bao bì luân chuyển | G77: 2 | H77: x | K77: Asset
B78: =C78&D78&E78 -> 1532101 | C78: 153 | D78: 21 | E78: 01 | F78: Bao bì luân chuyển | G78: 3 | K78: Asset
B79: =C79&D79&E79 -> 1533000 | C79: 153 | D79: 30 | E79: 00 | F79: Đồ dùng cho thuê | G79: 2 | H79: x | K79: Asset
B80: =C80&D80&E80 -> 1533101 | C80: 153 | D80: 31 | E80: 01 | F80: Đồ dùng cho thuê | G80: 3 | K80: Asset
B81: =C81&D81&E81 -> 1534000 | C81: 153 | D81: 40 | E81: 00 | F81: Thiết bị, phụ tùng thay thế | G81: 2 | H81: x | K81: Asset
B82: =C82&D82&E82 -> 1534101 | C82: 153 | D82: 41 | E82: 01 | F82: Thiết bị, phụ tùng thay thế | G82: 3 | K82: Asset
B83: =C83&D83&E83 -> 1540000 | C83: 154 | D83: 00 | E83: 00 | F83: Chi phí sản xuất, kinh doanh dở dang | G83: 1 | H83: x | I83: BS141 | K83: Asset
B84: =C84&D84&E84 -> 1541000 | C84: 154 | D84: 10 | E84: 00 | F84: Chi phí sản xuất, kinh doanh dở dang | G84: 2 | H84: x | K84: Asset
B85: =C85&D85&E85 -> 1541101 | C85: 154 | D85: 11 | E85: 01 | F85: Chi phí sản xuất, kinh doanh dở dang | G85: 3 | K85: Asset
B86: =C86&D86&E86 -> 1550000 | C86: 155 | D86: 00 | E86: 00 | F86: Thành phẩm | G86: 1 | H86: x | I86: BS141 | K86: Asset
B87: =C87&D87&E87 -> 1551000 | C87: 155 | D87: 10 | E87: 00 | F87: Thành phẩm | G87: 2 | H87: x | K87: Asset
B88: =C88&D88&E88 -> 1551101 | C88: 155 | D88: 11 | E88: 01 | F88: Thành phẩm | G88: 3 | K88: Asset
B89: =C89&D89&E89 -> 1557000 | C89: 155 | D89: 70 | E89: 00 | F89: Thành phẩm bất động sản | G89: 2 | H89: x | K89: Asset
B90: =C90&D90&E90 -> 1557101 | C90: 155 | D90: 71 | E90: 01 | F90: Thành phẩm bất động sản | G90: 3 | K90: Asset
B91: =C91&D91&E91 -> 1560000 | C91: 156 | D91: 00 | E91: 00 | F91: Hàng hóa | G91: 1 | H91: x | I91: BS141 | K91: Asset
B92: =C92&D92&E92 -> 1561000 | C92: 156 | D92: 10 | E92: 00 | F92: Giá mua hàng hóa | G92: 2 | H92: x | K92: Asset
B93: =C93&D93&E93 -> 1561101 | C93: 156 | D93: 11 | E93: 01 | F93: Giá mua hàng hóa | G93: 3 | K93: Asset
B94: =C94&D94&E94 -> 1570000 | C94: 157 | D94: 00 | E94: 00 | F94: Hàng gửi đi bán | G94: 1 | H94: x | I94: BS141 | K94: Asset
B95: =C95&D95&E95 -> 1571000 | C95: 157 | D95: 10 | E95: 00 | F95: Hàng gửi đi bán | G95: 2 | H95: x | K95: Asset
B96: =C96&D96&E96 -> 1571101 | C96: 157 | D96: 11 | E96: 01 | F96: Hàng gửi đi bán | G96: 3 | K96: Asset
B97: =C97&D97&E97 -> 2110000 | C97: 211 | D97: 00 | E97: 00 | F97: Tài sản cố định hữu hình | G97: 1 | H97: x | I97: BS222 | K97: Asset
B98: =C98&D98&E98 -> 2111000 | C98: 211 | D98: 10 | E98: 00 | F98: Tài sản cố định hữu hình | G98: 2 | H98: x | K98: Asset
B99: =C99&D99&E99 -> 2111101 | C99: 211 | D99: 11 | E99: 01 | F99: Nhà cửa, vật kiến trúc | G99: 3 | K99: Asset
B100: =C100&D100&E100 -> 2112000 | C100: 211 | D100: 20 | E100: 00 | F100: Máy móc, thiết bị | G100: 2 | H100: x | K100: Asset
B101: =C101&D101&E101 -> 2112101 | C101: 211 | D101: 21 | E101: 01 | F101: Máy móc, thiết bị | G101: 3 | K101: Asset
B102: =C102&D102&E102 -> 2113000 | C102: 211 | D102: 30 | E102: 00 | F102: Phương tiện vận tải, truyền dẫn | G102: 2 | H102: x | K102: Asset
...

Sheet Seg 2 TK Ngoại bảng
A1: Tài khoản Ngoài bảng
A3: Số tài khoản | B3: Tên tài khoản | C3: Parent
A4: 001 | B4: Tài sản thuê ngoài
A5: 002 | B5: Vật tư, hàng hoá nhận giữ hộ, nhận gia công
A6: 003 | B6: Hàng hoá nhận bán hộ, nhận ký gửi, ký cược
A7: 004 | B7: Nợ khó đòi đã xử lý
A8: 007 | B8: Ngoại tệ các loại
A9: 008 | B9: Dự toán chi sự nghiệp, dự án

Sheet Seg 3 - Sub Acc
A1: Segment 3 : xx.xxx(Chi tiết tài khoản - Sub Account)
A2: Biến phí, Định phí có thể Group theo Nhóm chi phí không, để đưa vào PL theo Group chi phí | J2: Check Ngân sách: YTD-QTD
A3: Mã | B3: Giá trị | C3: Nhóm | D3: Parent | E3: Level | F3: Thuộc tài khoản | G3: Mã Cost center | H3: Tên Cost center | I3: Check thực hiện và KH | J3: Budget control (Y/N) | K3: ĐP/BP | L3: Lập PR (Y/N) | M3: Ghi chú
A4: 11000 | B4: TIỀN MẶT | C4: BS | D4: x | E4: 1
A5: 11001 | B5: TM-HCM | C5: BS | E5: 2 | F5: ='Seg 2_Account'!B8 -> 1111101
A6: =A5+1 -> 11002 | B6: TM-NHA TRANG | C6: BS | E6: 2 | F6: =$F$5 -> 1111101
A7: =A6+1 -> 11003 | B7: TM-ĐẮC LẮC | C7: BS | E7: 2 | F7: =$F$5 -> 1111101
A8: =A7+1 -> 11004 | B8: TM-ĐÀ NẴNG | C8: BS | E8: 2 | F8: =$F$5 -> 1111101
A9: =A8+1 -> 11005 | B9: TM-HÀ NỘI | C9: BS | E9: 2 | F9: =$F$5 -> 1111101
A10: =A9+1 -> 11006 | B10: TM-CẦN THƠ | C10: BS | E10: 2 | F10: =$F$5 -> 1111101
A11: 12000 | B11: NGÂN HÀNG | C11: BS | D11: x | E11: 1
A12: 12001 | B12: VTB-KHANHHOA-VND-8467 | C12: BS | E12: 2 | F12: ='Seg 2_Account'!B13 -> 1121101
A13: =A12+1 -> 12002 | B13: VCB-KHANHHOA-VND-5620 | C13: BS | E13: 2 | F13: ='Seg 2_Account'!B14 -> 1121102
A14: =A13+1 -> 12003 | B14: VCB-HOANGVANTHU-VND-0750 | C14: BS | E14: 2 | F14: =$F$13 -> 1121102
A15: =A14+1 -> 12004 | B15: VCB-DANANG-VND-3063 | C15: BS | E15: 2 | F15: =$F$13 -> 1121102
A16: =A15+1 -> 12005 | B16: VCB-DAKLAK-VND-6693 | C16: BS | E16: 2 | F16: =$F$13 -> 1121102
A17: =A16+1 -> 12006 | B17: VCB-HANOI-VND-0515 | C17: BS | E17: 2 | F17: =$F$13 -> 1121102
A18: =A17+1 -> 12007 | B18: VCB-KHANHHOA-USD-7004 | C18: BS | E18: 2 | F18: ='Seg 2_Account'!B16 -> 1122101
A19: 24000 | B19: Xây dựng cơ bản dở dang | C19: BS | D19: x | E19: 1 | M19: Trong SubAccount, nếu cần theo dõi tập hợp chi phí xây dựng theo từng đối tượng như Kho Tân Thuận, Kho Đà Nẵng…thì sẽ thực hiện thế nào?
A20: 24001 | B20: Tủ đông | C20: BS | E20: 2 | F20: ='Seg 2_Account'!$B$177 -> 2411101 | G20: =#REF! -> #REF! | H20: =VLOOKUP($G20,#REF!,2,0) -> #REF! | I20: x | J20: Y | L20: Y | N20: Updated 16/10/2024
A21: =A20+1 -> 24002 | B21: Kho | C21: BS | E21: 2 | F21: ='Seg 2_Account'!B180 -> 2412101 | G21: =#REF! -> #REF! | H21: =VLOOKUP($G21,#REF!,2,0) -> #REF! | I21: x | J21: Y | L21: Y | N21: Updated 16/10/2024
A22: =A21+1 -> 24003 | B22: Phần mềm | C22: BS | E22: 2 | F22: =$F$21 -> 2412101 | G22: All | H22: All (except BP Ban điều hành) | I22: x | J22: Y | L22: Y | N22: Updated 16/10/2024
A23: =A22+1 -> 24004 | B23: Quyền sử dụng đất | C23: BS | E23: 2 | F23: =$F$21 -> 2412101 | I23: x
A24: =A23+1 -> 24005 | B24: Phương tiện vận tải | C24: BS | E24: 2 | F24: ='Seg 2_Account'!$B$177 -> 2411101 | G24: =#REF! -> #REF! | H24: =VLOOKUP($G24,#REF!,2,0) -> #REF! | I24: x | J24: Y | L24: Y | N24: Updated 16/10/2024
A25: 51000 | B25: Doanh thu hoạt động tài chính | C25: PL1 | D25: x | E25: 1
A26: 51001 | B26: Lãi cho Cá nhân vay | C26: PL1 | E26: 2 | F26: ='Seg 2_Account'!B373 -> 5152000
A27: =A26+1 -> 51002 | B27: Lãi cho Công ty vay | C27: PL1 | E27: 2 | F27: =$F$26 -> 5152000
A28: =A27+1 -> 51003 | B28: Lãi trả chậm, trả góp | C28: PL1 | E28: 2 | F28: =$F$26 -> 5152000
A29: =A28+1 -> 51004 | B29: Thu nhập về hoạt động đầu tư mua, bán chứng khoán | C29: PL1 | E29: 2 | F29: =$F$26 -> 5152000
A30: =A29+1 -> 51005 | B30: Lãi từ hoạt động chuyển nhượng vốn | C30: PL1 | E30: 2 | F30: =$F$26 -> 5152000
A31: =A30+1 -> 51006 | B31: Thu nhập về các hoạt động đầu tư khác | C31: PL1 | E31: 2 | F31: =$F$26 -> 5152000
A32: =A31+1 -> 51007 | B32: Lãi tỷ giá hối đoái | C32: PL1 | E32: 2 | F32: ='Seg 2_Account'!$B$375&", "&'Seg 2_Account'!$B$376 -> 5152102, 5153000
A33: =A32+1 -> 51008 | B33: Chiết khấu thanh toán được hưởng từ NCC | C33: PL1 | E33: 2 | F33: ='Seg 2_Account'!B378 -> 5158000
A34: =A33+1 -> 51009 | B34: Lãi tiền gửi ngân hàng | C34: PL1 | E34: 2 | F34: ='Seg 2_Account'!B380 -> 5210000
A35: 51999 | B35: Doanh thu hoạt động tài chính khác | C35: PL1 | E35: 2 | F35: =F34 -> 5210000
A36: 52000 | B36: Chi phí hoạt động tài chính | C36: PL1 | D36: x | E36: 1
A37: 52001 | B37: Chi phí lãi vay Cá nhân | C37: PL1 | E37: 2 | F37: ='Seg 2_Account'!B414 -> 6351000 | I37: x | M37: Có cần tách không?
A38: =A37+1 -> 52002 | B38: Chi phí lãi vay Tổ chức tín dụng | C38: PL1 | E38: 2 | F38: =$F$37 -> 6351000 | I38: x | M38: Có cần tách không?
A39: =A38+1 -> 52003 | B39: Lỗ tỷ giá hối đoái | C39: PL1 | E39: 2 | F39: ='Seg 2_Account'!B416&","& 'Seg 2_Account'!B417 -> 6352000,6352101 | I39: x
A40: =A39+1 -> 52004 | B40: Chiết khấu thanh toán cho khách hàng | C40: PL1 | E40: 2 | F40: ='Seg 2_Account'!B419 -> 6353000 | I40: x
A41: =A40+1 -> 52005 | B41: Chi phí trích lập dự phòng giảm giá chứng khoán | C41: PL1 | E41: 2 | F41: ='Seg 2_Account'!B421 -> 6354000 | I41: x
A42: =A41+1 -> 52006 | B42: Chi phí trích lập dự phòng tổn thất đầu tư vào các đơn vị khác | C42: PL1 | E42: 2 | F42: =F41 -> 6354000 | I42: x
A43: =A42+1 -> 52007 | B43: Lỗ từ hoạt động chuyển nhượng vốn | C43: PL1 | E43: 2 | F43: ='Seg 2_Account'!B422 -> 6354101 | I43: x
A44: =A43+1 -> 52008 | B44: Lỗ chuyển nhượng chứng khoán | C44: PL1 | E44: 2 | F44: =F43 -> 6354101 | I44: x
A45: =A44+1 -> 52009 | B45: Chi phí giao dịch bán chứng khoán | C45: PL1 | E45: 2 | F45: =F43 -> 6354101 | I45: x
A46: =A45+1 -> 52010 | B46: Chi phí hoạt động tài chính khác | C46: PL1 | E46: 2 | F46: ='Seg 2_Account'!B424 -> 6358000 | I46: x
A47: 61000 | B47: Chi phí nhân sự | C47: PL1 | D47: x | E47: 1 | F47: ='Seg 2_Account'!B427&", "&'Seg 2_Account'!B444 -> 6411000, 6421000 | I47: x
A48: 61001 | B48: Chi phí lương nhân viên | C48: PL1 | E48: 2 | F48: =$F$47 -> 6411000, 6421000 | G48: All | H48: All | I48: x
A49: =A48+1 -> 61002 | B49: Chi phí lương KPI | C49: PL1 | E49: 2 | F49: =$F$47 -> 6411000, 6421000 | G49: All | H49: All | I49: x | K49: BP
A50: =A49+1 -> 61003 | B50: Chi phí lương hiệu quả kinh doanh | C50: PL1 | E50: 2 | F50: =$F$47 -> 6411000, 6421000 | G50: All | H50: All | I50: x | K50: BP
A51: =A50+1 -> 61004 | B51: Chi phí phụ cấp nhân viên, phúc lợi | C51: PL1 | E51: 2 | F51: =$F$47 -> 6411000, 6421000 | G51: All | H51: All | I51: x
A52: =A51+1 -> 61005 | B52: Chi phí lương nhân viên tháng 13 | C52: PL1 | E52: 2 | F52: =$F$47 -> 6411000, 6421000 | G52: All | H52: All | I52: x
A53: =A52+1 -> 61006 | B53: Chi phí lương nhân viên thời vụ | C53: PL1 | E53: 2 | F53: =$F$47 -> 6411000, 6421000 | G53: All | H53: All | I53: x
A54: =A53+1 -> 61007 | B54: Chi phí bảo hiểm xã hội | C54: PL1 | E54: 2 | F54: =$F$47 -> 6411000, 6421000 | G54: All | H54: All | I54: x
A55: =A54+1 -> 61008 | B55: Chi phí bảo hiểm y tế | C55: PL1 | E55: 2 | F55: =$F$47 -> 6411000, 6421000 | G55: All | H55: All | I55: x
A56: =A55+1 -> 61009 | B56: Chi phí bảo hiểm thất nghiệp | C56: PL1 | E56: 2 | F56: =$F$47 -> 6411000, 6421000 | G56: All | H56: All | I56: x
A57: =A56+1 -> 61010 | B57: Chi phí bảo hiểm con người | C57: PL1 | E57: 2 | F57: =$F$47 -> 6411000, 6421000 | G57: All | H57: All | I57: x
A58: =A57+1 -> 61011 | B58: Chi phí công đoàn | C58: PL1 | E58: 2 | F58: =$F$47 -> 6411000, 6421000 | G58: All | H58: All | I58: x
A59: =A58+1 -> 61012 | B59: Chi phí tuyển dụng, đào tạo | C59: PL1 | E59: 2 | F59: =$F$47 -> 6411000, 6421000 | G59: All | H59: All | I59: x
A60: =A59+1 -> 61013 | B60: Chi phí đồng phục | C60: PL1 | E60: 2 | F60: =$F$47 -> 6411000, 6421000 | G60: All | H60: All | I60: x
A61: =A60+1 -> 61014 | B61: Chi phí khám sức khỏe | C61: PL1 | E61: 2 | F61: =$F$47 -> 6411000, 6421000 | G61: All | H61: All | I61: x
A62: 61099 | B62: Chi phí nhân sự khác | C62: PL1 | E62: 2 | F62: =$F$47 -> 6411000, 6421000 | G62: All | H62: All | I62: x
A63: 62000 | B63: Chi phí bao bì, vật tư | C63: PL1 | D63: x | E63: 1 | F63: ='Seg 2_Account'!B429&", "&'Seg 2_Account'!B446 -> 6412000, 6422000
A64: 62001 | B64: Chi phí decal, bao bì, trang trí, in ấn…phục vụ bán hàng | C64: PL1 | E64: 2 | F64: ='Seg 2_Account'!B429 -> 6412000 | G64: =#REF! -> #REF! | H64: =VLOOKUP($G64,#REF!,2,0) -> #REF! | I64: x | L64: Y
A65: =A64+1 -> 62002 | B65: Chi phí tem nhãn | C65: PL1 | E65: 2 | F65: =F64 -> 6412000 | G65: =#REF! -> #REF! | H65: =VLOOKUP($G65,#REF!,2,0) -> #REF! | I65: x | K65: BP | L65: Y | M65: Aron tư vấn nên là BP hay ĐP
A66: 62999 | B66: Chi phí bao bì, vật tư khác | C66: PL1 | E66: 2 | F66: =$F$63 -> 6412000, 6422000 | G66: All | H66: All | I66: x | L66: Y
A67: 63000 | B67: Chi phí công cụ, dụng cụ, đồ dùng | C67: PL1 | D67: x | E67: 1 | F67: ='Seg 2_Account'!B431&", "&'Seg 2_Account'!B448 -> 6413000, 6423000
A68: 63001 | B68: Chi phí phân bổ tủ đông | C68: PL1 | E68: 2 | F68: =$F$67 -> 6413000, 6423000 | G68: =#REF! -> #REF! | H68: =VLOOKUP($G68,#REF!,2,0) -> #REF! | I68: x
A69: =A68+1 -> 63002 | B69: Chi phí vật dụng xe tải | C69: PL1 | E69: 2 | F69: =$F$67 -> 6413000, 6423000 | G69: =#REF! -> #REF! | H69: =VLOOKUP($G69,#REF!,2,0) -> #REF! | I69: x
A70: =A69+1 -> 63003 | B70: Chi phí thiết bị, dụng cụ, đồ dùng văn phòng | C70: PL1 | E70: 2 | F70: =$F$67 -> 6413000, 6423000 | G70: All | H70: All | I70: x | L70: Y
A71: =A70+1 -> 63004 | B71: Chi phí sửa chữa, bảo trì thiết bị văn phòng | C71: PL1 | E71: 2 | F71: =$F$67 -> 6413000, 6423000 | G71: All | H71: All | I71: x | L71: Y
A72: =A71+1 -> 63005 | B72: Chi phí mua văn phòng phẩm | C72: PL1 | E72: 2 | F72: =$F$67 -> 6413000, 6423000 | G72: All | H72: All (except BP Ban điều hành) | I72: x | J72: Y | L72: Y | N72: Updated 16/10/2024
A73: =A72+1 -> 63006 | B73: Chi phí mua đồng phục | C73: PL1 | E73: 2 | F73: =$F$67 -> 6413000, 6423000 | G73: All | H73: All | I73: x | L73: Y
A74: =A73+1 -> 63007 | B74: Chi phí hủy hàng | C74: PL1 | E74: 2 | F74: ='Seg 2_Account'!$B$409 -> 6323000 | G74: =#REF! -> #REF! | H74: =VLOOKUP($G74,#REF!,2,0) -> #REF! | I74: x | N74: Updated 16/10/2024
A75: =A74+1 -> 63008 | B75: Chi phí hao hụt, mất mát hàng hóa | C75: PL1 | E75: 2 | F75: ='Seg 2_Account'!$B$409 -> 6323000 | G75: =#REF! -> #REF! | H75: =VLOOKUP($G75,#REF!,2,0) -> #REF! | I75: x | N75: Updated 16/10/2024
A76: 63999 | B76: Chi phí dụng cụ, đồ dùng văn phòng khác | C76: PL1 | E76: 2 | F76: =$F$67 -> 6413000, 6423000 | G76: All | H76: All | I76: x
A77: 64000 | B77: Chi phí khấu hao | C77: PL1 | D77: x | E77: 1 | F77: ='Seg 2_Account'!B433&", "&'Seg 2_Account'!B450 -> 6414000, 6424000
A78: 64001 | B78: Khấu hao/Nhà cửa, vật kiến trúc | C78: PL1 | E78: 2 | F78: =$F$77 -> 6414000, 6424000 | G78: All | H78: All | I78: x
A79: =A78+1 -> 64002 | B79: Khấu hao/Máy móc, thiết bị | C79: PL1 | E79: 2 | F79: =$F$77 -> 6414000, 6424000 | G79: All | H79: All | I79: x
A80: =A79+1 -> 64003 | B80: Khấu hao/Phương tiện vận tải | C80: PL1 | E80: 2 | F80: =$F$77 -> 6414000, 6424000 | G80: All | H80: All | I80: x
A81: =A80+1 -> 64004 | B81: Khấu hao/Thiết bị, dụng cụ quản lý | C81: PL1 | E81: 2 | F81: =$F$77 -> 6414000, 6424000 | G81: All | H81: All | I81: x
A82: =A81+1 -> 64005 | B82: Khấu hao/TSCĐHH khác | C82: PL1 | E82: 2 | F82: =$F$77 -> 6414000, 6424000 | G82: All | H82: All | I82: x
A83: =A82+1 -> 64006 | B83: Khấu hao TSVH/Quyền sử dụng đất | C83: PL1 | E83: 2 | F83: =$F$77 -> 6414000, 6424000 | G83: All | H83: All | I83: x
A84: =A83+1 -> 64007 | B84: Khấu hao TSVH /Quyền phát hành | C84: PL1 | E84: 2 | F84: =$F$77 -> 6414000, 6424000 | G84: All | H84: All | I84: x
A85: =A84+1 -> 64008 | B85: Khấu hao TSVH /Bản quyền, bằng sáng chế | C85: PL1 | E85: 2 | F85: =$F$77 -> 6414000, 6424000 | G85: All | H85: All | I85: x
A86: =A85+1 -> 64009 | B86: Khấu hao TSVH /Nhãn hiệu, tên thương mại | C86: PL1 | E86: 2 | F86: =$F$77 -> 6414000, 6424000 | G86: All | H86: All | I86: x
A87: =A86+1 -> 64010 | B87: Khấu hao TSVH/Phần mềm quản lý | C87: PL1 | E87: 2 | F87: =$F$77 -> 6414000, 6424000 | G87: All | H87: All | I87: x
A88: =A87+1 -> 64011 | B88: Khấu hao TSVH /Giấy phép và giấy phép nhượng quyền | C88: PL1 | E88: 2 | F88: =$F$77 -> 6414000, 6424000 | G88: All | H88: All | I88: x
A89: =A88+1 -> 64012 | B89: Khấu hao TSVH /Khác | C89: PL1 | E89: 2 | F89: =$F$77 -> 6414000, 6424000 | G89: All | H89: All | I89: x
A90: 65000 | B90: Chi phí thuế, phí | C90: PL1 | D90: x | E90: 1 | F90: ='Seg 2_Account'!B452 -> 6425000
A91: 65001 | B91: Thuế bảo vệ môi trường | C91: PL1 | E91: 2 | F91: =$F$90 -> 6425000 | G91: =#REF! -> #REF! | H91: =VLOOKUP($G91,#REF!,2,0) -> #REF! | I91: x
A92: =A91+1 -> 65002 | B92: Thuế môn bài | C92: PL1 | E92: 2 | F92: =$F$90 -> 6425000 | G92: =$G$91 -> #REF! | H92: =VLOOKUP($G92,#REF!,2,0) -> #REF! | I92: x
A93: =A92+1 -> 65003 | B93: Thuế thuê nhà (GTGT+TNCN) | C93: PL1 | E93: 2 | F93: =$F$90 -> 6425000 | G93: =$G$91 -> #REF! | H93: =VLOOKUP($G93,#REF!,2,0) -> #REF! | I93: x
A94: =A93+1 -> 65004 | B94: Thuế nhà thầu (GTGT+TNCN) | C94: PL1 | E94: 2 | F94: =$F$90 -> 6425000 | G94: =$G$91 -> #REF! | H94: =VLOOKUP($G94,#REF!,2,0) -> #REF! | I94: x
A95: =A94+1 -> 65005 | B95: Thuế GTGT phân bổ không được khấu trừ | C95: PL1 | E95: 2 | F95: =$F$90 -> 6425000 | G95: =$G$91 -> #REF! | H95: =VLOOKUP($G95,#REF!,2,0) -> #REF! | I95: x
A96: 65099 | B96: Các khoản phí và lệ phí khác | C96: PL1 | E96: 2 | F96: =$F$90 -> 6425000 | G96: =$G$91 -> #REF! | H96: =VLOOKUP($G96,#REF!,2,0) -> #REF! | I96: x
A97: 66000 | B97: Chi phí hỗ trợ bán hàng | C97: PL1 | D97: x | E97: 1 | F97: ='Seg 2_Account'!B437 -> 6416000
A98: 66001 | B98: Chi phí hỗ trợ bán hàng theo trading term | C98: PL1 | E98: 2 | F98: =$F$97 -> 6416000 | G98: =#REF! -> #REF! | H98: =VLOOKUP($G98,#REF!,2,0) -> #REF! | I98: x | K98: BP
A99: =A98+1 -> 66002 | B99: Chi phí hỗ trợ bán hàng ngoài trading term | C99: PL1 | E99: 2 | F99: =$F$97 -> 6416000 | G99: =$G$98 -> #REF! | H99: =VLOOKUP($G99,#REF!,2,0) -> #REF! | I99: x | K99: BP
A100: =A99+1 -> 66003 | B100: Chi phí khuyến mãi, chào hàng, chào mẫu | C100: PL1 | E100: 2 | F100: =$F$97 -> 6416000 | G100: =#REF! -> #REF! | H100: =VLOOKUP($G100,#REF!,2,0) -> #REF! | I100: x | J100: Y | K100: BP | M100: Lập Phiếu yêu cầu, sau khi được duyệt sẽ tạo SO (type khuyến mãi/chào hàng/chào mẫu...) | N100: Updated 16/10/2024
...

Sheet Seg 4_Cost center-DeptSite1
A2: Segment 4: x.xx.xx (Cost Center) | J2: Mã Khối.Mã Bộ phận.Mã Site
A4: Mã Khối | B4: Tên Khối | C4: Mã Bộ phận | D4: Tên BP | E4: Mã Site | F4: Tên site | G4: Ký hiệu site | H4: Mã COA | I4: Diễn giải | J4: Parent | K4: level
C5: 0000 | H5: 0000 | I5: Mặc định
A6: 1 | B6: Khối Trực tiếp | H6: 10000 | I6: Khối Trực Tiếp | J6: x | K6: 1
C7: 111 | D7: Bộ phận Kinh doanh | H7: =C7&"00" -> 11100 | I7: =D7 -> Bộ phận Kinh doanh | K7: 2
C8: =$C$7 -> 111 | D8: Bộ phận Kinh doanh | E8: 10 | F8: =VLOOKUP($E8,'Bo phan'!$B$31:$D$39,2,0) -> Hồ Chí Minh | G8: =VLOOKUP($E8,'Bo phan'!$B$31:$D$39,3,0) -> HCM | H8: =C8&E8 -> 11110 | I8: =G8&"."&D8 -> HCM.Bộ phận Kinh doanh | K8: 3
C9: =$C$7 -> 111 | D9: Bộ phận Kinh doanh | E9: 20 | F9: =VLOOKUP(E9,'Bo phan'!$B$31:$D$39,2,0) -> Nha Trang | G9: =VLOOKUP($E9,'Bo phan'!$B$31:$D$39,3,0) -> NTR | H9: =C9&E9 -> 11120 | I9: =G9&"."&D9 -> NTR.Bộ phận Kinh doanh | K9: 3
C10: =$C$7 -> 111 | D10: Bộ phận Kinh doanh | E10: 30 | F10: =VLOOKUP(E10,'Bo phan'!$B$31:$D$39,2,0) -> Đắc Lắc | G10: =VLOOKUP($E10,'Bo phan'!$B$31:$D$39,3,0) -> DLA | H10: =C10&E10 -> 11130 | I10: =G10&"."&D10 -> DLA.Bộ phận Kinh doanh | K10: 3
C11: =$C$7 -> 111 | D11: Bộ phận Kinh doanh | E11: 40 | F11: =VLOOKUP(E11,'Bo phan'!$B$31:$D$39,2,0) -> Đà Nẵng | G11: =VLOOKUP($E11,'Bo phan'!$B$31:$D$39,3,0) -> DNG | H11: =C11&E11 -> 11140 | I11: =G11&"."&D11 -> DNG.Bộ phận Kinh doanh | K11: 3
C12: =$C$7 -> 111 | D12: Bộ phận Kinh doanh | E12: 50 | F12: =VLOOKUP(E12,'Bo phan'!$B$31:$D$39,2,0) -> Hà Nội | G12: =VLOOKUP($E12,'Bo phan'!$B$31:$D$39,3,0) -> HNO | H12: =C12&E12 -> 11150 | I12: =G12&"."&D12 -> HNO.Bộ phận Kinh doanh | K12: 3
C13: =$C$7 -> 111 | D13: Bộ phận Kinh doanh | E13: 60 | F13: =VLOOKUP(E13,'Bo phan'!$B$31:$D$39,2,0) -> Cần Thơ | G13: =VLOOKUP($E13,'Bo phan'!$B$31:$D$39,3,0) -> CTH | H13: =C13&E13 -> 11160 | I13: =G13&"."&D13 -> CTH.Bộ phận Kinh doanh | K13: 3
C14: 112 | D14: Bộ phận Logistic - Quản lý | H14: =C14&"00" -> 11200 | I14: =D14 -> Bộ phận Logistic - Quản lý | K14: 2
C15: =$C$14 -> 112 | D15: Bộ phận Logistic - Quản lý | E15: 10 | F15: =VLOOKUP($E15,'Bo phan'!$B$31:$D$39,2,0) -> Hồ Chí Minh | G15: =VLOOKUP($E15,'Bo phan'!$B$31:$D$39,3,0) -> HCM | H15: =C15&E15 -> 11210 | I15: =G15&"."&D15 -> HCM.Bộ phận Logistic - Quản lý | K15: 3
C16: =$C$14 -> 112 | D16: Bộ phận Logistic - Quản lý | E16: 20 | F16: =VLOOKUP(E16,'Bo phan'!$B$31:$D$39,2,0) -> Nha Trang | G16: =VLOOKUP($E16,'Bo phan'!$B$31:$D$39,3,0) -> NTR | H16: =C16&E16 -> 11220 | I16: =G16&"."&D16 -> NTR.Bộ phận Logistic - Quản lý | K16: 3
C17: =$C$14 -> 112 | D17: Bộ phận Logistic - Quản lý | E17: 30 | F17: =VLOOKUP(E17,'Bo phan'!$B$31:$D$39,2,0) -> Đắc Lắc | G17: =VLOOKUP($E17,'Bo phan'!$B$31:$D$39,3,0) -> DLA | H17: =C17&E17 -> 11230 | I17: =G17&"."&D17 -> DLA.Bộ phận Logistic - Quản lý | K17: 3
C18: =$C$14 -> 112 | D18: Bộ phận Logistic - Quản lý | E18: 40 | F18: =VLOOKUP(E18,'Bo phan'!$B$31:$D$39,2,0) -> Đà Nẵng | G18: =VLOOKUP($E18,'Bo phan'!$B$31:$D$39,3,0) -> DNG | H18: =C18&E18 -> 11240 | I18: =G18&"."&D18 -> DNG.Bộ phận Logistic - Quản lý | K18: 3
C19: =$C$14 -> 112 | D19: Bộ phận Logistic - Quản lý | E19: 50 | F19: =VLOOKUP(E19,'Bo phan'!$B$31:$D$39,2,0) -> Hà Nội | G19: =VLOOKUP($E19,'Bo phan'!$B$31:$D$39,3,0) -> HNO | H19: =C19&E19 -> 11250 | I19: =G19&"."&D19 -> HNO.Bộ phận Logistic - Quản lý | K19: 3
C20: =$C$14 -> 112 | D20: Bộ phận Logistic - Quản lý | E20: 60 | F20: =VLOOKUP(E20,'Bo phan'!$B$31:$D$39,2,0) -> Cần Thơ | G20: =VLOOKUP($E20,'Bo phan'!$B$31:$D$39,3,0) -> CTH | H20: =C20&E20 -> 11260 | I20: =G20&"."&D20 -> CTH.Bộ phận Logistic - Quản lý | K20: 3
C21: 113 | D21: Bộ phận Logistic - Kho | H21: =C21&"00" -> 11300 | I21: =D21 -> Bộ phận Logistic - Kho | J21: x | K21: 2
C22: =$C$21 -> 113 | D22: Bộ phận Logistic - Kho | E22: 10 | F22: =VLOOKUP($E22,'Bo phan'!$B$31:$D$39,2,0) -> Hồ Chí Minh | G22: =VLOOKUP($E22,'Bo phan'!$B$31:$D$39,3,0) -> HCM | H22: =C22&E22 -> 11310 | I22: =G22&"."&D22 -> HCM.Bộ phận Logistic - Kho | K22: 3
C23: =$C$21 -> 113 | D23: Bộ phận Logistic - Kho | E23: 20 | F23: =VLOOKUP(E23,'Bo phan'!$B$31:$D$39,2,0) -> Nha Trang | G23: =VLOOKUP($E23,'Bo phan'!$B$31:$D$39,3,0) -> NTR | H23: =C23&E23 -> 11320 | I23: =G23&"."&D23 -> NTR.Bộ phận Logistic - Kho | K23: 3
C24: =$C$21 -> 113 | D24: Bộ phận Logistic - Kho | E24: 30 | F24: =VLOOKUP(E24,'Bo phan'!$B$31:$D$39,2,0) -> Đắc Lắc | G24: =VLOOKUP($E24,'Bo phan'!$B$31:$D$39,3,0) -> DLA | H24: =C24&E24 -> 11330 | I24: =G24&"."&D24 -> DLA.Bộ phận Logistic - Kho | K24: 3
C25: =$C$21 -> 113 | D25: Bộ phận Logistic - Kho | E25: 40 | F25: =VLOOKUP(E25,'Bo phan'!$B$31:$D$39,2,0) -> Đà Nẵng | G25: =VLOOKUP($E25,'Bo phan'!$B$31:$D$39,3,0) -> DNG | H25: =C25&E25 -> 11340 | I25: =G25&"."&D25 -> DNG.Bộ phận Logistic - Kho | K25: 3
C26: =$C$21 -> 113 | D26: Bộ phận Logistic - Kho | E26: 50 | F26: =VLOOKUP(E26,'Bo phan'!$B$31:$D$39,2,0) -> Hà Nội | G26: =VLOOKUP($E26,'Bo phan'!$B$31:$D$39,3,0) -> HNO | H26: =C26&E26 -> 11350 | I26: =G26&"."&D26 -> HNO.Bộ phận Logistic - Kho | K26: 3
C27: =$C$21 -> 113 | D27: Bộ phận Logistic - Kho | E27: 60 | F27: =VLOOKUP(E27,'Bo phan'!$B$31:$D$39,2,0) -> Cần Thơ | G27: =VLOOKUP($E27,'Bo phan'!$B$31:$D$39,3,0) -> CTH | H27: =C27&E27 -> 11360 | I27: =G27&"."&D27 -> CTH.Bộ phận Logistic - Kho | K27: 3
C28: 114 | D28: Bộ phận Logistic - Giao nhận | H28: =C28&"00" -> 11400 | I28: =D28 -> Bộ phận Logistic - Giao nhận | J28: x | K28: 2
C29: =$C$28 -> 114 | D29: Bộ phận Logistic - Giao nhận | E29: 10 | F29: =VLOOKUP($E29,'Bo phan'!$B$31:$D$39,2,0) -> Hồ Chí Minh | G29: =VLOOKUP($E29,'Bo phan'!$B$31:$D$39,3,0) -> HCM | H29: =C29&E29 -> 11410 | I29: =G29&"."&D29 -> HCM.Bộ phận Logistic - Giao nhận | K29: 3
C30: =$C$28 -> 114 | D30: Bộ phận Logistic - Giao nhận | E30: 20 | F30: =VLOOKUP(E30,'Bo phan'!$B$31:$D$39,2,0) -> Nha Trang | G30: =VLOOKUP($E30,'Bo phan'!$B$31:$D$39,3,0) -> NTR | H30: =C30&E30 -> 11420 | I30: =G30&"."&D30 -> NTR.Bộ phận Logistic - Giao nhận | K30: 3
C31: =$C$28 -> 114 | D31: Bộ phận Logistic - Giao nhận | E31: 30 | F31: =VLOOKUP(E31,'Bo phan'!$B$31:$D$39,2,0) -> Đắc Lắc | G31: =VLOOKUP($E31,'Bo phan'!$B$31:$D$39,3,0) -> DLA | H31: =C31&E31 -> 11430 | I31: =G31&"."&D31 -> DLA.Bộ phận Logistic - Giao nhận | K31: 3
C32: =$C$28 -> 114 | D32: Bộ phận Logistic - Giao nhận | E32: 40 | F32: =VLOOKUP(E32,'Bo phan'!$B$31:$D$39,2,0) -> Đà Nẵng | G32: =VLOOKUP($E32,'Bo phan'!$B$31:$D$39,3,0) -> DNG | H32: =C32&E32 -> 11440 | I32: =G32&"."&D32 -> DNG.Bộ phận Logistic - Giao nhận | K32: 3
C33: =$C$28 -> 114 | D33: Bộ phận Logistic - Giao nhận | E33: 50 | F33: =VLOOKUP(E33,'Bo phan'!$B$31:$D$39,2,0) -> Hà Nội | G33: =VLOOKUP($E33,'Bo phan'!$B$31:$D$39,3,0) -> HNO | H33: =C33&E33 -> 11450 | I33: =G33&"."&D33 -> HNO.Bộ phận Logistic - Giao nhận | K33: 3
C34: =$C$28 -> 114 | D34: Bộ phận Logistic - Giao nhận | E34: 60 | F34: =VLOOKUP(E34,'Bo phan'!$B$31:$D$39,2,0) -> Cần Thơ | G34: =VLOOKUP($E34,'Bo phan'!$B$31:$D$39,3,0) -> CTH | H34: =C34&E34 -> 11460 | I34: =G34&"."&D34 -> CTH.Bộ phận Logistic - Giao nhận | K34: 3
C35: 115 | D35: Bộ phận Marketing | H35: =C35&"00" -> 11500 | I35: =D35 -> Bộ phận Marketing | J35: x | K35: 2
C36: =$C$35 -> 115 | D36: Bộ phận Marketing | E36: 10 | F36: =VLOOKUP($E36,'Bo phan'!$B$31:$D$39,2,0) -> Hồ Chí Minh | G36: =VLOOKUP($E36,'Bo phan'!$B$31:$D$39,3,0) -> HCM | H36: =C36&E36 -> 11510 | I36: =G36&"."&D36 -> HCM.Bộ phận Marketing | K36: 3
C37: =$C$35 -> 115 | D37: Bộ phận Marketing | E37: 20 | F37: =VLOOKUP(E37,'Bo phan'!$B$31:$D$39,2,0) -> Nha Trang | G37: =VLOOKUP($E37,'Bo phan'!$B$31:$D$39,3,0) -> NTR | H37: =C37&E37 -> 11520 | I37: =G37&"."&D37 -> NTR.Bộ phận Marketing | K37: 3
C38: =$C$35 -> 115 | D38: Bộ phận Marketing | E38: 30 | F38: =VLOOKUP(E38,'Bo phan'!$B$31:$D$39,2,0) -> Đắc Lắc | G38: =VLOOKUP($E38,'Bo phan'!$B$31:$D$39,3,0) -> DLA | H38: =C38&E38 -> 11530 | I38: =G38&"."&D38 -> DLA.Bộ phận Marketing | K38: 3
C39: =$C$35 -> 115 | D39: Bộ phận Marketing | E39: 40 | F39: =VLOOKUP(E39,'Bo phan'!$B$31:$D$39,2,0) -> Đà Nẵng | G39: =VLOOKUP($E39,'Bo phan'!$B$31:$D$39,3,0) -> DNG | H39: =C39&E39 -> 11540 | I39: =G39&"."&D39 -> DNG.Bộ phận Marketing | K39: 3
C40: =$C$35 -> 115 | D40: Bộ phận Marketing | E40: 50 | F40: =VLOOKUP(E40,'Bo phan'!$B$31:$D$39,2,0) -> Hà Nội | G40: =VLOOKUP($E40,'Bo phan'!$B$31:$D$39,3,0) -> HNO | H40: =C40&E40 -> 11550 | I40: =G40&"."&D40 -> HNO.Bộ phận Marketing | K40: 3
C41: =$C$35 -> 115 | D41: Bộ phận Marketing | E41: 60 | F41: =VLOOKUP(E41,'Bo phan'!$B$31:$D$39,2,0) -> Cần Thơ | G41: =VLOOKUP($E41,'Bo phan'!$B$31:$D$39,3,0) -> CTH | H41: =C41&E41 -> 11560 | I41: =G41&"."&D41 -> CTH.Bộ phận Marketing | K41: 3
C42: 116 | D42: Bộ phận Trade Marketing | H42: =C42&"00" -> 11600 | I42: =D42 -> Bộ phận Trade Marketing | J42: x | K42: 2
C43: =$C$42 -> 116 | D43: Bộ phận Trade Marketing | E43: 10 | F43: =VLOOKUP($E43,'Bo phan'!$B$31:$D$39,2,0) -> Hồ Chí Minh | G43: =VLOOKUP($E43,'Bo phan'!$B$31:$D$39,3,0) -> HCM | H43: =C43&E43 -> 11610 | I43: =G43&"."&D43 -> HCM.Bộ phận Trade Marketing | K43: 3
C44: =$C$42 -> 116 | D44: Bộ phận Trade Marketing | E44: 20 | F44: =VLOOKUP(E44,'Bo phan'!$B$31:$D$39,2,0) -> Nha Trang | G44: =VLOOKUP($E44,'Bo phan'!$B$31:$D$39,3,0) -> NTR | H44: =C44&E44 -> 11620 | I44: =G44&"."&D44 -> NTR.Bộ phận Trade Marketing | K44: 3
C45: =$C$42 -> 116 | D45: Bộ phận Trade Marketing | E45: 30 | F45: =VLOOKUP(E45,'Bo phan'!$B$31:$D$39,2,0) -> Đắc Lắc | G45: =VLOOKUP($E45,'Bo phan'!$B$31:$D$39,3,0) -> DLA | H45: =C45&E45 -> 11630 | I45: =G45&"."&D45 -> DLA.Bộ phận Trade Marketing | K45: 3
C46: =$C$42 -> 116 | D46: Bộ phận Trade Marketing | E46: 40 | F46: =VLOOKUP(E46,'Bo phan'!$B$31:$D$39,2,0) -> Đà Nẵng | G46: =VLOOKUP($E46,'Bo phan'!$B$31:$D$39,3,0) -> DNG | H46: =C46&E46 -> 11640 | I46: =G46&"."&D46 -> DNG.Bộ phận Trade Marketing | K46: 3
C47: =$C$42 -> 116 | D47: Bộ phận Trade Marketing | E47: 50 | F47: =VLOOKUP(E47,'Bo phan'!$B$31:$D$39,2,0) -> Hà Nội | G47: =VLOOKUP($E47,'Bo phan'!$B$31:$D$39,3,0) -> HNO | H47: =C47&E47 -> 11650 | I47: =G47&"."&D47 -> HNO.Bộ phận Trade Marketing | K47: 3
C48: =$C$42 -> 116 | D48: Bộ phận Trade Marketing | E48: 60 | F48: =VLOOKUP(E48,'Bo phan'!$B$31:$D$39,2,0) -> Cần Thơ | G48: =VLOOKUP($E48,'Bo phan'!$B$31:$D$39,3,0) -> CTH | H48: =C48&E48 -> 11660 | I48: =G48&"."&D48 -> CTH.Bộ phận Trade Marketing | K48: 3
A49: 2 | B49: Khối Gián tiếp | H49: 20000 | I49: Khối Gián Tiếp | K49: 1
C50: 211 | D50: Bộ phận Ban Điều hành | H50: =C50&"00" -> 21100 | I50: =D50 -> Bộ phận Ban Điều hành | J50: x | K50: 2
C51: =$C$50 -> 211 | D51: Bộ phận Ban Điều hành | E51: 10 | F51: =VLOOKUP($E51,'Bo phan'!$B$31:$D$39,2,0) -> Hồ Chí Minh | G51: =VLOOKUP($E51,'Bo phan'!$B$31:$D$39,3,0) -> HCM | H51: =C51&E51 -> 21110 | I51: =G51&"."&D51 -> HCM.Bộ phận Ban Điều hành | K51: 3
C52: =$C$50 -> 211 | D52: Bộ phận Ban Điều hành | E52: 20 | F52: =VLOOKUP(E52,'Bo phan'!$B$31:$D$39,2,0) -> Nha Trang | G52: =VLOOKUP($E52,'Bo phan'!$B$31:$D$39,3,0) -> NTR | H52: =C52&E52 -> 21120 | I52: =G52&"."&D52 -> NTR.Bộ phận Ban Điều hành | K52: 3
C53: =$C$50 -> 211 | D53: Bộ phận Ban Điều hành | E53: 30 | F53: =VLOOKUP(E53,'Bo phan'!$B$31:$D$39,2,0) -> Đắc Lắc | G53: =VLOOKUP($E53,'Bo phan'!$B$31:$D$39,3,0) -> DLA | H53: =C53&E53 -> 21130 | I53: =G53&"."&D53 -> DLA.Bộ phận Ban Điều hành | K53: 3
C54: =$C$50 -> 211 | D54: Bộ phận Ban Điều hành | E54: 40 | F54: =VLOOKUP(E54,'Bo phan'!$B$31:$D$39,2,0) -> Đà Nẵng | G54: =VLOOKUP($E54,'Bo phan'!$B$31:$D$39,3,0) -> DNG | H54: =C54&E54 -> 21140 | I54: =G54&"."&D54 -> DNG.Bộ phận Ban Điều hành | K54: 3
C55: =$C$50 -> 211 | D55: Bộ phận Ban Điều hành | E55: 50 | F55: =VLOOKUP(E55,'Bo phan'!$B$31:$D$39,2,0) -> Hà Nội | G55: =VLOOKUP($E55,'Bo phan'!$B$31:$D$39,3,0) -> HNO | H55: =C55&E55 -> 21150 | I55: =G55&"."&D55 -> HNO.Bộ phận Ban Điều hành | K55: 3
C56: =$C$50 -> 211 | D56: Bộ phận Ban Điều hành | E56: 60 | F56: =VLOOKUP(E56,'Bo phan'!$B$31:$D$39,2,0) -> Cần Thơ | G56: =VLOOKUP($E56,'Bo phan'!$B$31:$D$39,3,0) -> CTH | H56: =C56&E56 -> 21160 | I56: =G56&"."&D56 -> CTH.Bộ phận Ban Điều hành | K56: 3
C57: 212 | D57: Bộ phận Tài chính - Kế toán | H57: =C57&"00" -> 21200 | I57: =D57 -> Bộ phận Tài chính - Kế toán | J57: x | K57: 2
C58: =$C$57 -> 212 | D58: Bộ phận Tài chính - Kế toán | E58: 10 | F58: =VLOOKUP($E58,'Bo phan'!$B$31:$D$39,2,0) -> Hồ Chí Minh | G58: =VLOOKUP($E58,'Bo phan'!$B$31:$D$39,3,0) -> HCM | H58: =C58&E58 -> 21210 | I58: =G58&"."&D58 -> HCM.Bộ phận Tài chính - Kế toán | K58: 3
C59: =$C$57 -> 212 | D59: Bộ phận Tài chính - Kế toán | E59: 20 | F59: =VLOOKUP(E59,'Bo phan'!$B$31:$D$39,2,0) -> Nha Trang | G59: =VLOOKUP($E59,'Bo phan'!$B$31:$D$39,3,0) -> NTR | H59: =C59&E59 -> 21220 | I59: =G59&"."&D59 -> NTR.Bộ phận Tài chính - Kế toán | K59: 3
C60: =$C$57 -> 212 | D60: Bộ phận Tài chính - Kế toán | E60: 30 | F60: =VLOOKUP(E60,'Bo phan'!$B$31:$D$39,2,0) -> Đắc Lắc | G60: =VLOOKUP($E60,'Bo phan'!$B$31:$D$39,3,0) -> DLA | H60: =C60&E60 -> 21230 | I60: =G60&"."&D60 -> DLA.Bộ phận Tài chính - Kế toán | K60: 3
C61: =$C$57 -> 212 | D61: Bộ phận Tài chính - Kế toán | E61: 40 | F61: =VLOOKUP(E61,'Bo phan'!$B$31:$D$39,2,0) -> Đà Nẵng | G61: =VLOOKUP($E61,'Bo phan'!$B$31:$D$39,3,0) -> DNG | H61: =C61&E61 -> 21240 | I61: =G61&"."&D61 -> DNG.Bộ phận Tài chính - Kế toán | K61: 3
C62: =$C$57 -> 212 | D62: Bộ phận Tài chính - Kế toán | E62: 50 | F62: =VLOOKUP(E62,'Bo phan'!$B$31:$D$39,2,0) -> Hà Nội | G62: =VLOOKUP($E62,'Bo phan'!$B$31:$D$39,3,0) -> HNO | H62: =C62&E62 -> 21250 | I62: =G62&"."&D62 -> HNO.Bộ phận Tài chính - Kế toán | K62: 3
C63: =$C$57 -> 212 | D63: Bộ phận Tài chính - Kế toán | E63: 60 | F63: =VLOOKUP(E63,'Bo phan'!$B$31:$D$39,2,0) -> Cần Thơ | G63: =VLOOKUP($E63,'Bo phan'!$B$31:$D$39,3,0) -> CTH | H63: =C63&E63 -> 21260 | I63: =G63&"."&D63 -> CTH.Bộ phận Tài chính - Kế toán | K63: 3
C64: 213 | D64: Bộ phận Hành chính - Nhân sự | H64: =C64&"00" -> 21300 | I64: =D64 -> Bộ phận Hành chính - Nhân sự | J64: x | K64: 2
C65: =$C$64 -> 213 | D65: Bộ phận Hành chính - Nhân sự | E65: 10 | F65: =VLOOKUP($E65,'Bo phan'!$B$31:$D$39,2,0) -> Hồ Chí Minh | G65: =VLOOKUP($E65,'Bo phan'!$B$31:$D$39,3,0) -> HCM | H65: =C65&E65 -> 21310 | I65: =G65&"."&D65 -> HCM.Bộ phận Hành chính - Nhân sự | K65: 3
C66: =$C$64 -> 213 | D66: Bộ phận Hành chính - Nhân sự | E66: 20 | F66: =VLOOKUP(E66,'Bo phan'!$B$31:$D$39,2,0) -> Nha Trang | G66: =VLOOKUP($E66,'Bo phan'!$B$31:$D$39,3,0) -> NTR | H66: =C66&E66 -> 21320 | I66: =G66&"."&D66 -> NTR.Bộ phận Hành chính - Nhân sự | K66: 3
C67: =$C$64 -> 213 | D67: Bộ phận Hành chính - Nhân sự | E67: 30 | F67: =VLOOKUP(E67,'Bo phan'!$B$31:$D$39,2,0) -> Đắc Lắc | G67: =VLOOKUP($E67,'Bo phan'!$B$31:$D$39,3,0) -> DLA | H67: =C67&E67 -> 21330 | I67: =G67&"."&D67 -> DLA.Bộ phận Hành chính - Nhân sự | K67: 3
C68: =$C$64 -> 213 | D68: Bộ phận Hành chính - Nhân sự | E68: 40 | F68: =VLOOKUP(E68,'Bo phan'!$B$31:$D$39,2,0) -> Đà Nẵng | G68: =VLOOKUP($E68,'Bo phan'!$B$31:$D$39,3,0) -> DNG | H68: =C68&E68 -> 21340 | I68: =G68&"."&D68 -> DNG.Bộ phận Hành chính - Nhân sự | K68: 3
C69: =$C$64 -> 213 | D69: Bộ phận Hành chính - Nhân sự | E69: 50 | F69: =VLOOKUP(E69,'Bo phan'!$B$31:$D$39,2,0) -> Hà Nội | G69: =VLOOKUP($E69,'Bo phan'!$B$31:$D$39,3,0) -> HNO | H69: =C69&E69 -> 21350 | I69: =G69&"."&D69 -> HNO.Bộ phận Hành chính - Nhân sự | K69: 3
C70: =$C$64 -> 213 | D70: Bộ phận Hành chính - Nhân sự | E70: 60 | F70: =VLOOKUP(E70,'Bo phan'!$B$31:$D$39,2,0) -> Cần Thơ | G70: =VLOOKUP($E70,'Bo phan'!$B$31:$D$39,3,0) -> CTH | H70: =C70&E70 -> 21360 | I70: =G70&"."&D70 -> CTH.Bộ phận Hành chính - Nhân sự | K70: 3
C71: 214 | D71: Bộ phận Kế hoạch | H71: =C71&"00" -> 21400 | I71: =D71 -> Bộ phận Kế hoạch | J71: x | K71: 2
C72: =$C$71 -> 214 | D72: Bộ phận Kế hoạch | E72: 10 | F72: =VLOOKUP($E72,'Bo phan'!$B$31:$D$39,2,0) -> Hồ Chí Minh | G72: =VLOOKUP($E72,'Bo phan'!$B$31:$D$39,3,0) -> HCM | H72: =C72&E72 -> 21410 | I72: =G72&"."&D72 -> HCM.Bộ phận Kế hoạch | K72: 3
C73: =$C$71 -> 214 | D73: Bộ phận Kế hoạch | E73: 20 | F73: =VLOOKUP(E73,'Bo phan'!$B$31:$D$39,2,0) -> Nha Trang | G73: =VLOOKUP($E73,'Bo phan'!$B$31:$D$39,3,0) -> NTR | H73: =C73&E73 -> 21420 | I73: =G73&"."&D73 -> NTR.Bộ phận Kế hoạch | K73: 3
C74: =$C$71 -> 214 | D74: Bộ phận Kế hoạch | E74: 30 | F74: =VLOOKUP(E74,'Bo phan'!$B$31:$D$39,2,0) -> Đắc Lắc | G74: =VLOOKUP($E74,'Bo phan'!$B$31:$D$39,3,0) -> DLA | H74: =C74&E74 -> 21430 | I74: =G74&"."&D74 -> DLA.Bộ phận Kế hoạch | K74: 3
C75: =$C$71 -> 214 | D75: Bộ phận Kế hoạch | E75: 40 | F75: =VLOOKUP(E75,'Bo phan'!$B$31:$D$39,2,0) -> Đà Nẵng | G75: =VLOOKUP($E75,'Bo phan'!$B$31:$D$39,3,0) -> DNG | H75: =C75&E75 -> 21440 | I75: =G75&"."&D75 -> DNG.Bộ phận Kế hoạch | K75: 3
C76: =$C$71 -> 214 | D76: Bộ phận Kế hoạch | E76: 50 | F76: =VLOOKUP(E76,'Bo phan'!$B$31:$D$39,2,0) -> Hà Nội | G76: =VLOOKUP($E76,'Bo phan'!$B$31:$D$39,3,0) -> HNO | H76: =C76&E76 -> 21450 | I76: =G76&"."&D76 -> HNO.Bộ phận Kế hoạch | K76: 3
C77: =$C$71 -> 214 | D77: Bộ phận Kế hoạch | E77: 60 | F77: =VLOOKUP(E77,'Bo phan'!$B$31:$D$39,2,0) -> Cần Thơ | G77: =VLOOKUP($E77,'Bo phan'!$B$31:$D$39,3,0) -> CTH | H77: =C77&E77 -> 21460 | I77: =G77&"."&D77 -> CTH.Bộ phận Kế hoạch | K77: 3
C78: 215 | D78: Bộ phận Xuất nhập khẩu | H78: =C78&"00" -> 21500 | I78: =D78 -> Bộ phận Xuất nhập khẩu | J78: x | K78: 2
C79: =$C$78 -> 215 | D79: Bộ phận Xuất nhập khẩu | E79: 10 | F79: =VLOOKUP($E79,'Bo phan'!$B$31:$D$39,2,0) -> Hồ Chí Minh | G79: =VLOOKUP($E79,'Bo phan'!$B$31:$D$39,3,0) -> HCM | H79: =C79&E79 -> 21510 | I79: =G79&"."&D79 -> HCM.Bộ phận Xuất nhập khẩu | K79: 3
C80: =$C$78 -> 215 | D80: Bộ phận Xuất nhập khẩu | E80: 20 | F80: =VLOOKUP(E80,'Bo phan'!$B$31:$D$39,2,0) -> Nha Trang | G80: =VLOOKUP($E80,'Bo phan'!$B$31:$D$39,3,0) -> NTR | H80: =C80&E80 -> 21520 | I80: =G80&"."&D80 -> NTR.Bộ phận Xuất nhập khẩu | K80: 3
C81: =$C$78 -> 215 | D81: Bộ phận Xuất nhập khẩu | E81: 30 | F81: =VLOOKUP(E81,'Bo phan'!$B$31:$D$39,2,0) -> Đắc Lắc | G81: =VLOOKUP($E81,'Bo phan'!$B$31:$D$39,3,0) -> DLA | H81: =C81&E81 -> 21530 | I81: =G81&"."&D81 -> DLA.Bộ phận Xuất nhập khẩu | K81: 3
C82: =$C$78 -> 215 | D82: Bộ phận Xuất nhập khẩu | E82: 40 | F82: =VLOOKUP(E82,'Bo phan'!$B$31:$D$39,2,0) -> Đà Nẵng | G82: =VLOOKUP($E82,'Bo phan'!$B$31:$D$39,3,0) -> DNG | H82: =C82&E82 -> 21540 | I82: =G82&"."&D82 -> DNG.Bộ phận Xuất nhập khẩu | K82: 3
C83: =$C$78 -> 215 | D83: Bộ phận Xuất nhập khẩu | E83: 50 | F83: =VLOOKUP(E83,'Bo phan'!$B$31:$D$39,2,0) -> Hà Nội | G83: =VLOOKUP($E83,'Bo phan'!$B$31:$D$39,3,0) -> HNO | H83: =C83&E83 -> 21550 | I83: =G83&"."&D83 -> HNO.Bộ phận Xuất nhập khẩu | K83: 3
C84: =$C$78 -> 215 | D84: Bộ phận Xuất nhập khẩu | E84: 60 | F84: =VLOOKUP(E84,'Bo phan'!$B$31:$D$39,2,0) -> Cần Thơ | G84: =VLOOKUP($E84,'Bo phan'!$B$31:$D$39,3,0) -> CTH | H84: =C84&E84 -> 21560 | I84: =G84&"."&D84 -> CTH.Bộ phận Xuất nhập khẩu | K84: 3
C85: 216 | D85: Bộ phận Sourcing | H85: =C85&"00" -> 21600 | I85: =D85 -> Bộ phận Sourcing | J85: x | K85: 2
C86: =$C$85 -> 216 | D86: Bộ phận Sourcing | E86: 10 | F86: =VLOOKUP($E86,'Bo phan'!$B$31:$D$39,2,0) -> Hồ Chí Minh | G86: =VLOOKUP($E86,'Bo phan'!$B$31:$D$39,3,0) -> HCM | H86: =C86&E86 -> 21610 | I86: =G86&"."&D86 -> HCM.Bộ phận Sourcing | K86: 3
C87: =$C$85 -> 216 | D87: Bộ phận Sourcing | E87: 20 | F87: =VLOOKUP(E87,'Bo phan'!$B$31:$D$39,2,0) -> Nha Trang | G87: =VLOOKUP($E87,'Bo phan'!$B$31:$D$39,3,0) -> NTR | H87: =C87&E87 -> 21620 | I87: =G87&"."&D87 -> NTR.Bộ phận Sourcing | K87: 3
C88: =$C$85 -> 216 | D88: Bộ phận Sourcing | E88: 30 | F88: =VLOOKUP(E88,'Bo phan'!$B$31:$D$39,2,0) -> Đắc Lắc | G88: =VLOOKUP($E88,'Bo phan'!$B$31:$D$39,3,0) -> DLA | H88: =C88&E88 -> 21630 | I88: =G88&"."&D88 -> DLA.Bộ phận Sourcing | K88: 3
C89: =$C$85 -> 216 | D89: Bộ phận Sourcing | E89: 40 | F89: =VLOOKUP(E89,'Bo phan'!$B$31:$D$39,2,0) -> Đà Nẵng | G89: =VLOOKUP($E89,'Bo phan'!$B$31:$D$39,3,0) -> DNG | H89: =C89&E89 -> 21640 | I89: =G89&"."&D89 -> DNG.Bộ phận Sourcing | K89: 3
C90: =$C$85 -> 216 | D90: Bộ phận Sourcing | E90: 50 | F90: =VLOOKUP(E90,'Bo phan'!$B$31:$D$39,2,0) -> Hà Nội | G90: =VLOOKUP($E90,'Bo phan'!$B$31:$D$39,3,0) -> HNO | H90: =C90&E90 -> 21650 | I90: =G90&"."&D90 -> HNO.Bộ phận Sourcing | K90: 3
C91: =$C$85 -> 216 | D91: Bộ phận Sourcing | E91: 60 | F91: =VLOOKUP(E91,'Bo phan'!$B$31:$D$39,2,0) -> Cần Thơ | G91: =VLOOKUP($E91,'Bo phan'!$B$31:$D$39,3,0) -> CTH | H91: =C91&E91 -> 21660 | I91: =G91&"."&D91 -> CTH.Bộ phận Sourcing | K91: 3
C92: 217 | D92: Bộ phận Mua hàng | H92: =C92&"00" -> 21700 | I92: =D92 -> Bộ phận Mua hàng | J92: x | K92: 2
C93: =$C$92 -> 217 | D93: Bộ phận Mua hàng | E93: 10 | F93: =VLOOKUP($E93,'Bo phan'!$B$31:$D$39,2,0) -> Hồ Chí Minh | G93: =VLOOKUP($E93,'Bo phan'!$B$31:$D$39,3,0) -> HCM | H93: =C93&E93 -> 21710 | I93: =G93&"."&D93 -> HCM.Bộ phận Mua hàng | K93: 3
C94: =$C$92 -> 217 | D94: Bộ phận Mua hàng | E94: 20 | F94: =VLOOKUP(E94,'Bo phan'!$B$31:$D$39,2,0) -> Nha Trang | G94: =VLOOKUP($E94,'Bo phan'!$B$31:$D$39,3,0) -> NTR | H94: =C94&E94 -> 21720 | I94: =G94&"."&D94 -> NTR.Bộ phận Mua hàng | K94: 3
C95: =$C$92 -> 217 | D95: Bộ phận Mua hàng | E95: 30 | F95: =VLOOKUP(E95,'Bo phan'!$B$31:$D$39,2,0) -> Đắc Lắc | G95: =VLOOKUP($E95,'Bo phan'!$B$31:$D$39,3,0) -> DLA | H95: =C95&E95 -> 21730 | I95: =G95&"."&D95 -> DLA.Bộ phận Mua hàng | K95: 3
C96: =$C$92 -> 217 | D96: Bộ phận Mua hàng | E96: 40 | F96: =VLOOKUP(E96,'Bo phan'!$B$31:$D$39,2,0) -> Đà Nẵng | G96: =VLOOKUP($E96,'Bo phan'!$B$31:$D$39,3,0) -> DNG | H96: =C96&E96 -> 21740 | I96: =G96&"."&D96 -> DNG.Bộ phận Mua hàng | K96: 3
C97: =$C$92 -> 217 | D97: Bộ phận Mua hàng | E97: 50 | F97: =VLOOKUP(E97,'Bo phan'!$B$31:$D$39,2,0) -> Hà Nội | G97: =VLOOKUP($E97,'Bo phan'!$B$31:$D$39,3,0) -> HNO | H97: =C97&E97 -> 21750 | I97: =G97&"."&D97 -> HNO.Bộ phận Mua hàng | K97: 3
C98: =$C$92 -> 217 | D98: Bộ phận Mua hàng | E98: 60 | F98: =VLOOKUP(E98,'Bo phan'!$B$31:$D$39,2,0) -> Cần Thơ | G98: =VLOOKUP($E98,'Bo phan'!$B$31:$D$39,3,0) -> CTH | H98: =C98&E98 -> 21760 | I98: =G98&"."&D98 -> CTH.Bộ phận Mua hàng | K98: 3
C99: 218 | D99: Bộ phận Công nghệ thông tin | H99: =C99&"00" -> 21800 | I99: =D99 -> Bộ phận Công nghệ thông tin | J99: x | K99: 2
C100: =$C$99 -> 218 | D100: Bộ phận Công nghệ thông tin | E100: 10 | F100: =VLOOKUP($E100,'Bo phan'!$B$31:$D$39,2,0) -> Hồ Chí Minh | G100: =VLOOKUP($E100,'Bo phan'!$B$31:$D$39,3,0) -> HCM | H100: =C100&E100 -> 21810 | I100: =G100&"."&D100 -> HCM.Bộ phận Công nghệ thông tin | K100: 3
C101: =$C$99 -> 218 | D101: Bộ phận Công nghệ thông tin | E101: 20 | F101: =VLOOKUP(E101,'Bo phan'!$B$31:$D$39,2,0) -> Nha Trang | G101: =VLOOKUP($E101,'Bo phan'!$B$31:$D$39,3,0) -> NTR | H101: =C101&E101 -> 21820 | I101: =G101&"."&D101 -> NTR.Bộ phận Công nghệ thông tin | K101: 3
C102: =$C$99 -> 218 | D102: Bộ phận Công nghệ thông tin | E102: 30 | F102: =VLOOKUP(E102,'Bo phan'!$B$31:$D$39,2,0) -> Đắc Lắc | G102: =VLOOKUP($E102,'Bo phan'!$B$31:$D$39,3,0) -> DLA | H102: =C102&E102 -> 21830 | I102: =G102&"."&D102 -> DLA.Bộ phận Công nghệ thông tin | K102: 3
...

Sheet Seg 6_Khu vực
B1: Segment 6 : xxxx (Khu vực - Area)
B3: Value | C3: Description | D3: Parent | E3: Level
B4: 0000 | C4: Mặc định | E4: 1
B5: 1000 | C5: Miền Nam | D5: x | E5: 1
B6: 1100 | C6: Hồ Chí Minh | D6: x | E6: 2
B7: 1101 | C7: Hồ Chí Minh | E7: 3
B8: 1200 | C8: Đông Nam Bộ | D8: x | E8: 2
B9: 1201 | C9: Bình Dương | E9: 3
B10: 1202 | C10: Vũng Tàu | E10: 3
B11: 1300 | C11: Tây Nam Bộ | D11: x | E11: 2
B12: 1301 | C12: Long An | E12: 3
B13: 1302 | C13: Đồng Nai | E13: 3
B14: 1303 | C14: Bến Tre
B15: 2000 | C15: Miền Bắc | D15: x | E15: 1
B16: 2100 | C16: Hà Nội | D16: x | E16: 2
B17: 2101 | C17: Hà Nội | E17: 3
B18: 2200 | C18: Đồng bằng Bắc Bộ | D18: x | E18: 2
B19: 2201 | C19: Bắc Ninh | E19: 3
B20: 2202 | C20: Hải Dương | E20: 3
B21: 2203 | C21: Hải Phòng | E21: 3
B22: 2204 | C22: Vĩnh Phúc | E22: 3
B23: 2300 | C23: Đông Bắc Bộ | D23: x | E23: 2
B24: 2301 | C24: Quảng Ninh | E24: 3
B25: 2302 | C25: Thái Nguyên | E25: 3
B27: 3000 | C27: Miền Trung & Tây Nguyên | D27: x | E27: 1
B28: 3100 | C28: Bắc Trung Bộ | D28: x | E28: 2
B29: 3101 | C29: Thanh Hóa | E29: 3
B30: 3200 | C30: Nam Trung Bộ | D30: x | E30: 2
B31: 3300 | C31: Tây Nguyên | D31: x | E31: 2
B32: 4000 | C32: Online | D32: x | E32: 1
B33: 4100 | C33: Online | D33: x | E33: 2
B34: 4101 | C34: Online | E34: 3

Sheet Seg 4_Location
A2: Segment 4 : x.xx.xx.xx.xx.xx (Vị trí - Location) | C2: Mã quốc gia. Mã miền.Mã vùng. Mã tỉnh thành. Mã quận huyện. Mã phường xã
A4: Mã | B4: Giá trị | C4: Parent | D4: Level
B5: Mặc định | D5: 1
B6: Kết chuyển | D6: 1
B7: Việt Nam | C7: x | D7: 1
B8: Miền Nam | C8: x | D8: 2
B9: Đông Nam Bộ | C9: x | D9: 3
B10: Hồ Chí Minh | C10: x | D10: 4
B11: Quận 1 | D11: 5
B12: Quận 2 | D12: 5
B13: Bình Dương | C13: x | D13: 4
B14: Thành phố Thủ Dầu Một | D14: 5
B15: Thành phố Dĩ An | D15: 5
B16: Đồng Nai | C16: x | D16: 4
B17: Thành phố Biên Hòa | D17: 5
B18: Huyện Thống Nhất | D18: 5
B19: Thành phố Vũng Tàu | C19: x | D19: 4
B20: Phường Thắng Nhất | D20: 5
B21: Phường Thắng Nhì | D21: 5
B22: Tây Nam Bộ | C22: x | D22: 3
B23: Long An | C23: x | D23: 4
B24: Thành phố Tân An | D24: 5
B25: Huyện Tân Hưng | D25: 5
B26: Tiền Giang | C26: x | D26: 4
B27: Thành phố Mỹ Tho | D27: 5
B28: Huyện Chợ Gạo | D28: 5
B29: Thành phố Cần Thơ | C29: x | D29: 4
B30: Quận Ninh Kiều | D30: 5
B31: Quận Cái Răng | D31: 5
B32: Miền Trung | C32: x | D32: 2
B33: Bắc Trung Bộ | C33: x | D33: 3
B34: Nghệ An | D34: 4
B35: Thanh Hóa | D35: 4
B36: Hà Tĩnh | D36: 4
B37: Quảng Bình | D37: 4
B38: Quảng Trị | D38: 4
B39: Thừa Thiên-Huế | D39: 4
B40: Nam Trung Bộ | C40: x | D40: 3
B41: Đà Nẵng | D41: 4
B42: Khánh Hoà | D42: 4
B43: Quảng Nam | D43: 4
B44: Ninh Thuận | D44: 4
B45: Bình Thuận | D45: 4
B46: Phú Yên | D46: 4
B47: Bình Định | D47: 4
B48: Quảng Ngãi | D48: 4
B49: Tây Nguyên | C49: x | D49: 3
B50: Lâm Đồng | D50: 4
B51: Kon Tum | D51: 4
B52: Gia Lai | D52: 4
B53: Đắc Lắc | D53: 4
B54: Miền Bắc | C54: x | D54: 2
B55: Đồng bằng sông Hồng | C55: x | D55: 3
B56: Hà Nội | D56: 4
B57: Quận Cầu Giấy | D57: 5
B58: Quận Đống Đa | D58: 5
B59: Bắc Ninh | D59: 4
B60: Thành phố Bắc Ninh | D60: 5
B61: Đông Bắc Bộ | C61: x | D61: 3
B62: Hà Giang | C62: x | D62: 4
B63: Thành phố Hà Giang | D63: 5
B64: Cao Bằng | C64: x | D64: 4
B65: Thành phố Cao Bằng | D65: 5
B66: Lạng Sơn | C66: x | D66: 4
B67: Thành phố Lạng Sơn | D67: 5
B68: Tây Bắc Bộ | C68: x | D68: 3
B69: Lào Cai | C69: x | D69: 4
B70: Thành phố Lào Cai | D70: 5
B71: Lai Châu | C71: x | D71: 4
B72: Phường Quyết Thắng | D72: 5

Sheet Seg 4_Cost center-SiteDept
A2: Segment 4: xx.xx (Phòng ban - Cost Center) | F2: Mã Site. Mã Bộ phận
A4: Mã Site | B4: Mã Bộ phận | C4: Tên BP | D4: Mã COA | E4: Diễn giải | F4: Parent | G4: level
A5: 0000 | B5: 0000 | D5: 0000 | E5: Mặc định
A6: 10 | B6: 00 | D6: 1000 | E6: HỒ CHÍ MINH | F6: x | G6: 1
A7: =$A$6 -> 10 | B7: 11 | C7: =VLOOKUP(B7,'[1]Bo phan'!$B$5:$C$25,2,0) -> Bộ phận Ban Điều hành | D7: =A7&B7 -> 1011 | E7: ="HCM."&C7 -> HCM.Bộ phận Ban Điều hành | G7: 2
A8: =$A$6 -> 10 | B8: =B7+1 -> 12 | C8: =VLOOKUP(B8,'[1]Bo phan'!$B$5:$C$25,2,0) -> Bộ phận Kinh doanh | D8: =A8&B8 -> 1012 | E8: ="HCM."&C8 -> HCM.Bộ phận Kinh doanh | G8: 2
A9: =$A$6 -> 10 | B9: =B8+1 -> 13 | C9: =VLOOKUP(B9,'[1]Bo phan'!$B$5:$C$25,2,0) -> Bộ phận Logistic - Quản lý | D9: =A9&B9 -> 1013 | E9: ="HCM."&C9 -> HCM.Bộ phận Logistic - Quản lý | G9: 2
A10: =$A$6 -> 10 | B10: =B9+1 -> 14 | C10: =VLOOKUP(B10,'[1]Bo phan'!$B$5:$C$25,2,0) -> Bộ phận Logistic - Kho | D10: =A10&B10 -> 1014 | E10: ="HCM."&C10 -> HCM.Bộ phận Logistic - Kho | G10: 2
A11: =$A$6 -> 10 | B11: =B10+1 -> 15 | C11: =VLOOKUP(B11,'[1]Bo phan'!$B$5:$C$25,2,0) -> Bộ phận Logistic - Giao nhận | D11: =A11&B11 -> 1015 | E11: ="HCM."&C11 -> HCM.Bộ phận Logistic - Giao nhận | G11: 2
A12: =$A$6 -> 10 | B12: =B11+1 -> 16 | C12: =VLOOKUP(B12,'[1]Bo phan'!$B$5:$C$25,2,0) -> Bộ phận Marketing | D12: =A12&B12 -> 1016 | E12: ="HCM."&C12 -> HCM.Bộ phận Marketing | G12: 2
A13: =$A$6 -> 10 | B13: =B12+1 -> 17 | C13: =VLOOKUP(B13,'[1]Bo phan'!$B$5:$C$25,2,0) -> Bộ phận Trade Marketing | D13: =A13&B13 -> 1017 | E13: ="HCM."&C13 -> HCM.Bộ phận Trade Marketing | G13: 2
A14: =$A$6 -> 10 | B14: =B13+1 -> 18 | C14: =VLOOKUP(B14,'[1]Bo phan'!$B$5:$C$25,2,0) -> Bộ phận Tài chính - Kế toán | D14: =A14&B14 -> 1018 | E14: ="HCM."&C14 -> HCM.Bộ phận Tài chính - Kế toán | G14: 2
A15: =$A$6 -> 10 | B15: =B14+1 -> 19 | C15: =VLOOKUP(B15,'[1]Bo phan'!$B$5:$C$25,2,0) -> Bộ phận Hành chính - Nhân sự | D15: =A15&B15 -> 1019 | E15: ="HCM."&C15 -> HCM.Bộ phận Hành chính - Nhân sự | G15: 2
A16: =$A$6 -> 10 | B16: =B15+1 -> 20 | C16: =VLOOKUP(B16,'[1]Bo phan'!$B$5:$C$25,2,0) -> Bộ phận Kế hoạch | D16: =A16&B16 -> 1020 | E16: ="HCM."&C16 -> HCM.Bộ phận Kế hoạch | G16: 2
A17: =$A$6 -> 10 | B17: =B16+1 -> 21 | C17: =VLOOKUP(B17,'[1]Bo phan'!$B$5:$C$25,2,0) -> Bộ phận Xuất nhập khẩu | D17: =A17&B17 -> 1021 | E17: ="HCM."&C17 -> HCM.Bộ phận Xuất nhập khẩu | G17: 2
A18: =$A$6 -> 10 | B18: =B17+1 -> 22 | C18: =VLOOKUP(B18,'[1]Bo phan'!$B$5:$C$25,2,0) -> Bộ phận Sourcing | D18: =A18&B18 -> 1022 | E18: ="HCM."&C18 -> HCM.Bộ phận Sourcing | G18: 2
A19: =$A$6 -> 10 | B19: =B18+1 -> 23 | C19: =VLOOKUP(B19,'[1]Bo phan'!$B$5:$C$25,2,0) -> Bộ phận Mua hàng | D19: =A19&B19 -> 1023 | E19: ="HCM."&C19 -> HCM.Bộ phận Mua hàng | G19: 2
... A24: =$A$6 -> 10 | B24: =B23+1 -> 28 | C24: =VLOOKUP(B24,'[1]Bo phan'!$B$5:$C$25,2,0) -> Bộ phận chung | D24: =A24&B24 -> 1028 | E24: ="HCM."&C24 -> HCM.Bộ phận chung | G24: 2
A25: 20 | B25: 00 | D25: 2000 | E25: NHA TRANG | F25: x | G25: 1
A26: =$A$25 -> 20 | B26: 11 | C26: =VLOOKUP(B26,'[1]Bo phan'!$B$5:$C$25,2,0) -> Bộ phận Ban Điều hành | D26: =A26&B26 -> 2011 | E26: ="NTR."&C26 -> NTR.Bộ phận Ban Điều hành | G26: 2
A27: =$A$25 -> 20 | B27: =B26+1 -> 12 | C27: =VLOOKUP(B27,'[1]Bo phan'!$B$5:$C$25,2,0) -> Bộ phận Kinh doanh | D27: =A27&B27 -> 2012 | E27: ="NTR."&C27 -> NTR.Bộ phận Kinh doanh | G27: 2
A28: =$A$25 -> 20 | B28: =B27+1 -> 13 | C28: =VLOOKUP(B28,'[1]Bo phan'!$B$5:$C$25,2,0) -> Bộ phận Logistic - Quản lý | D28: =A28&B28 -> 2013 | E28: ="NTR."&C28 -> NTR.Bộ phận Logistic - Quản lý | G28: 2
A29: =$A$25 -> 20 | B29: =B28+1 -> 14 | C29: =VLOOKUP(B29,'[1]Bo phan'!$B$5:$C$25,2,0) -> Bộ phận Logistic - Kho | D29: =A29&B29 -> 2014 | E29: ="NTR."&C29 -> NTR.Bộ phận Logistic - Kho | G29: 2
A30: =$A$25 -> 20 | B30: =B29+1 -> 15 | C30: =VLOOKUP(B30,'[1]Bo phan'!$B$5:$C$25,2,0) -> Bộ phận Logistic - Giao nhận | D30: =A30&B30 -> 2015 | E30: ="NTR."&C30 -> NTR.Bộ phận Logistic - Giao nhận | G30: 2
A31: =$A$25 -> 20 | B31: =B30+1 -> 16 | C31: =VLOOKUP(B31,'[1]Bo phan'!$B$5:$C$25,2,0) -> Bộ phận Marketing | D31: =A31&B31 -> 2016 | E31: ="NTR."&C31 -> NTR.Bộ phận Marketing | G31: 2
A32: =$A$25 -> 20 | B32: =B31+1 -> 17 | C32: =VLOOKUP(B32,'[1]Bo phan'!$B$5:$C$25,2,0) -> Bộ phận Trade Marketing | D32: =A32&B32 -> 2017 | E32: ="NTR."&C32 -> NTR.Bộ phận Trade Marketing | G32: 2
A33: =$A$25 -> 20 | B33: =B32+1 -> 18 | C33: =VLOOKUP(B33,'[1]Bo phan'!$B$5:$C$25,2,0) -> Bộ phận Tài chính - Kế toán | D33: =A33&B33 -> 2018 | E33: ="NTR."&C33 -> NTR.Bộ phận Tài chính - Kế toán | G33: 2
A34: =$A$25 -> 20 | B34: =B33+1 -> 19 | C34: =VLOOKUP(B34,'[1]Bo phan'!$B$5:$C$25,2,0) -> Bộ phận Hành chính - Nhân sự | D34: =A34&B34 -> 2019 | E34: ="NTR."&C34 -> NTR.Bộ phận Hành chính - Nhân sự | G34: 2
A35: =$A$25 -> 20 | B35: =B34+1 -> 20 | C35: =VLOOKUP(B35,'[1]Bo phan'!$B$5:$C$25,2,0) -> Bộ phận Kế hoạch | D35: =A35&B35 -> 2020 | E35: ="NTR."&C35 -> NTR.Bộ phận Kế hoạch | G35: 2
A36: =$A$25 -> 20 | B36: =B35+1 -> 21 | C36: =VLOOKUP(B36,'[1]Bo phan'!$B$5:$C$25,2,0) -> Bộ phận Xuất nhập khẩu | D36: =A36&B36 -> 2021 | E36: ="NTR."&C36 -> NTR.Bộ phận Xuất nhập khẩu | G36: 2
A37: =$A$25 -> 20 | B37: =B36+1 -> 22 | C37: =VLOOKUP(B37,'[1]Bo phan'!$B$5:$C$25,2,0) -> Bộ phận Sourcing | D37: =A37&B37 -> 2022 | E37: ="NTR."&C37 -> NTR.Bộ phận Sourcing | G37: 2
A38: =$A$25 -> 20 | B38: =B37+1 -> 23 | C38: =VLOOKUP(B38,'[1]Bo phan'!$B$5:$C$25,2,0) -> Bộ phận Mua hàng | D38: =A38&B38 -> 2023 | E38: ="NTR."&C38 -> NTR.Bộ phận Mua hàng | G38: 2
... A43: =$A$25 -> 20 | B43: =B42+1 -> 28 | C43: =VLOOKUP(B43,'[1]Bo phan'!$B$5:$C$25,2,0) -> Bộ phận chung | D43: =A43&B43 -> 2028 | E43: ="NTR."&C43 -> NTR.Bộ phận chung | G43: 2
A44: 30 | D44: 3000 | E44: ĐẮC LẮC | F44: x | G44: 1
A45: =$A$44 -> 30 | B45: 11 | C45: =VLOOKUP(B45,'[1]Bo phan'!$B$5:$C$25,2,0) -> Bộ phận Ban Điều hành | D45: =A45&B45 -> 3011 | E45: ="DLA."&C45 -> DLA.Bộ phận Ban Điều hành | G45: 2
A46: =$A$44 -> 30 | B46: =B45+1 -> 12 | C46: =VLOOKUP(B46,'[1]Bo phan'!$B$5:$C$25,2,0) -> Bộ phận Kinh doanh | D46: =A46&B46 -> 3012 | E46: ="DLA."&C46 -> DLA.Bộ phận Kinh doanh | G46: 2
A47: =$A$44 -> 30 | B47: =B46+1 -> 13 | C47: =VLOOKUP(B47,'[1]Bo phan'!$B$5:$C$25,2,0) -> Bộ phận Logistic - Quản lý | D47: =A47&B47 -> 3013 | E47: ="DLA."&C47 -> DLA.Bộ phận Logistic - Quản lý | G47: 2
A48: =$A$44 -> 30 | B48: =B47+1 -> 14 | C48: =VLOOKUP(B48,'[1]Bo phan'!$B$5:$C$25,2,0) -> Bộ phận Logistic - Kho | D48: =A48&B48 -> 3014 | E48: ="DLA."&C48 -> DLA.Bộ phận Logistic - Kho | G48: 2
A49: =$A$44 -> 30 | B49: =B48+1 -> 15 | C49: =VLOOKUP(B49,'[1]Bo phan'!$B$5:$C$25,2,0) -> Bộ phận Logistic - Giao nhận | D49: =A49&B49 -> 3015 | E49: ="DLA."&C49 -> DLA.Bộ phận Logistic - Giao nhận | G49: 2
A50: =$A$44 -> 30 | B50: =B49+1 -> 16 | C50: =VLOOKUP(B50,'[1]Bo phan'!$B$5:$C$25,2,0) -> Bộ phận Marketing | D50: =A50&B50 -> 3016 | E50: ="DLA."&C50 -> DLA.Bộ phận Marketing | G50: 2
A51: =$A$44 -> 30 | B51: =B50+1 -> 17 | C51: =VLOOKUP(B51,'[1]Bo phan'!$B$5:$C$25,2,0) -> Bộ phận Trade Marketing | D51: =A51&B51 -> 3017 | E51: ="DLA."&C51 -> DLA.Bộ phận Trade Marketing | G51: 2
A52: =$A$44 -> 30 | B52: =B51+1 -> 18 | C52: =VLOOKUP(B52,'[1]Bo phan'!$B$5:$C$25,2,0) -> Bộ phận Tài chính - Kế toán | D52: =A52&B52 -> 3018 | E52: ="DLA."&C52 -> DLA.Bộ phận Tài chính - Kế toán | G52: 2
A53: =$A$44 -> 30 | B53: =B52+1 -> 19 | C53: =VLOOKUP(B53,'[1]Bo phan'!$B$5:$C$25,2,0) -> Bộ phận Hành chính - Nhân sự | D53: =A53&B53 -> 3019 | E53: ="DLA."&C53 -> DLA.Bộ phận Hành chính - Nhân sự | G53: 2
A54: =$A$44 -> 30 | B54: =B53+1 -> 20 | C54: =VLOOKUP(B54,'[1]Bo phan'!$B$5:$C$25,2,0) -> Bộ phận Kế hoạch | D54: =A54&B54 -> 3020 | E54: ="DLA."&C54 -> DLA.Bộ phận Kế hoạch | G54: 2
A55: =$A$44 -> 30 | B55: =B54+1 -> 21 | C55: =VLOOKUP(B55,'[1]Bo phan'!$B$5:$C$25,2,0) -> Bộ phận Xuất nhập khẩu | D55: =A55&B55 -> 3021 | E55: ="DLA."&C55 -> DLA.Bộ phận Xuất nhập khẩu | G55: 2
A56: =$A$44 -> 30 | B56: =B55+1 -> 22 | C56: =VLOOKUP(B56,'[1]Bo phan'!$B$5:$C$25,2,0) -> Bộ phận Sourcing | D56: =A56&B56 -> 3022 | E56: ="DLA."&C56 -> DLA.Bộ phận Sourcing | G56: 2
A57: =$A$44 -> 30 | B57: =B56+1 -> 23 | C57: =VLOOKUP(B57,'[1]Bo phan'!$B$5:$C$25,2,0) -> Bộ phận Mua hàng | D57: =A57&B57 -> 3023 | E57: ="DLA."&C57 -> DLA.Bộ phận Mua hàng | G57: 2
... A62: =$A$44 -> 30 | B62: =B61+1 -> 28 | C62: =VLOOKUP(B62,'[1]Bo phan'!$B$5:$C$25,2,0) -> Bộ phận chung | D62: =A62&B62 -> 3028 | E62: ="DLA."&C62 -> DLA.Bộ phận chung | G62: 2
A63: 40 | D63: 4000 | E63: ĐÀ NẴNG | F63: x | G63: 1
A64: =$A$63 -> 40 | B64: 11 | C64: =VLOOKUP(B64,'[1]Bo phan'!$B$5:$C$25,2,0) -> Bộ phận Ban Điều hành | D64: =A64&B64 -> 4011 | E64: ="DNG."&C64 -> DNG.Bộ phận Ban Điều hành | G64: 2
A65: =$A$63 -> 40 | B65: =B64+1 -> 12 | C65: =VLOOKUP(B65,'[1]Bo phan'!$B$5:$C$25,2,0) -> Bộ phận Kinh doanh | D65: =A65&B65 -> 4012 | E65: ="DNG."&C65 -> DNG.Bộ phận Kinh doanh | G65: 2
A66: =$A$63 -> 40 | B66: =B65+1 -> 13 | C66: =VLOOKUP(B66,'[1]Bo phan'!$B$5:$C$25,2,0) -> Bộ phận Logistic - Quản lý | D66: =A66&B66 -> 4013 | E66: ="DNG."&C66 -> DNG.Bộ phận Logistic - Quản lý | G66: 2
A67: =$A$63 -> 40 | B67: =B66+1 -> 14 | C67: =VLOOKUP(B67,'[1]Bo phan'!$B$5:$C$25,2,0) -> Bộ phận Logistic - Kho | D67: =A67&B67 -> 4014 | E67: ="DNG."&C67 -> DNG.Bộ phận Logistic - Kho | G67: 2
A68: =$A$63 -> 40 | B68: =B67+1 -> 15 | C68: =VLOOKUP(B68,'[1]Bo phan'!$B$5:$C$25,2,0) -> Bộ phận Logistic - Giao nhận | D68: =A68&B68 -> 4015 | E68: ="DNG."&C68 -> DNG.Bộ phận Logistic - Giao nhận | G68: 2
A69: =$A$63 -> 40 | B69: =B68+1 -> 16 | C69: =VLOOKUP(B69,'[1]Bo phan'!$B$5:$C$25,2,0) -> Bộ phận Marketing | D69: =A69&B69 -> 4016 | E69: ="DNG."&C69 -> DNG.Bộ phận Marketing | G69: 2
A70: =$A$63 -> 40 | B70: =B69+1 -> 17 | C70: =VLOOKUP(B70,'[1]Bo phan'!$B$5:$C$25,2,0) -> Bộ phận Trade Marketing | D70: =A70&B70 -> 4017 | E70: ="DNG."&C70 -> DNG.Bộ phận Trade Marketing | G70: 2
A71: =$A$63 -> 40 | B71: =B70+1 -> 18 | C71: =VLOOKUP(B71,'[1]Bo phan'!$B$5:$C$25,2,0) -> Bộ phận Tài chính - Kế toán | D71: =A71&B71 -> 4018 | E71: ="DNG."&C71 -> DNG.Bộ phận Tài chính - Kế toán | G71: 2
A72: =$A$63 -> 40 | B72: =B71+1 -> 19 | C72: =VLOOKUP(B72,'[1]Bo phan'!$B$5:$C$25,2,0) -> Bộ phận Hành chính - Nhân sự | D72: =A72&B72 -> 4019 | E72: ="DNG."&C72 -> DNG.Bộ phận Hành chính - Nhân sự | G72: 2
A73: =$A$63 -> 40 | B73: =B72+1 -> 20 | C73: =VLOOKUP(B73,'[1]Bo phan'!$B$5:$C$25,2,0) -> Bộ phận Kế hoạch | D73: =A73&B73 -> 4020 | E73: ="DNG."&C73 -> DNG.Bộ phận Kế hoạch | G73: 2
A74: =$A$63 -> 40 | B74: =B73+1 -> 21 | C74: =VLOOKUP(B74,'[1]Bo phan'!$B$5:$C$25,2,0) -> Bộ phận Xuất nhập khẩu | D74: =A74&B74 -> 4021 | E74: ="DNG."&C74 -> DNG.Bộ phận Xuất nhập khẩu | G74: 2
A75: =$A$63 -> 40 | B75: =B74+1 -> 22 | C75: =VLOOKUP(B75,'[1]Bo phan'!$B$5:$C$25,2,0) -> Bộ phận Sourcing | D75: =A75&B75 -> 4022 | E75: ="DNG."&C75 -> DNG.Bộ phận Sourcing | G75: 2
A76: =$A$63 -> 40 | B76: =B75+1 -> 23 | C76: =VLOOKUP(B76,'[1]Bo phan'!$B$5:$C$25,2,0) -> Bộ phận Mua hàng | D76: =A76&B76 -> 4023 | E76: ="DNG."&C76 -> DNG.Bộ phận Mua hàng | G76: 2
... A81: =$A$63 -> 40 | B81: =B80+1 -> 28 | C81: =VLOOKUP(B81,'[1]Bo phan'!$B$5:$C$25,2,0) -> Bộ phận chung | D81: =A81&B81 -> 4028 | E81: ="DNG."&C81 -> DNG.Bộ phận chung | G81: 2
A82: 50 | D82: 5000 | E82: HÀ NỘI | F82: x | G82: 1
A83: =$A$82 -> 50 | B83: 11 | C83: =VLOOKUP(B83,'[1]Bo phan'!$B$5:$C$25,2,0) -> Bộ phận Ban Điều hành | D83: =A83&B83 -> 5011 | E83: ="HNO."&C83 -> HNO.Bộ phận Ban Điều hành | G83: 2
A84: =$A$82 -> 50 | B84: =B83+1 -> 12 | C84: =VLOOKUP(B84,'[1]Bo phan'!$B$5:$C$25,2,0) -> Bộ phận Kinh doanh | D84: =A84&B84 -> 5012 | E84: ="HNO."&C84 -> HNO.Bộ phận Kinh doanh | G84: 2
A85: =$A$82 -> 50 | B85: =B84+1 -> 13 | C85: =VLOOKUP(B85,'[1]Bo phan'!$B$5:$C$25,2,0) -> Bộ phận Logistic - Quản lý | D85: =A85&B85 -> 5013 | E85: ="HNO."&C85 -> HNO.Bộ phận Logistic - Quản lý | G85: 2
A86: =$A$82 -> 50 | B86: =B85+1 -> 14 | C86: =VLOOKUP(B86,'[1]Bo phan'!$B$5:$C$25,2,0) -> Bộ phận Logistic - Kho | D86: =A86&B86 -> 5014 | E86: ="HNO."&C86 -> HNO.Bộ phận Logistic - Kho | G86: 2
A87: =$A$82 -> 50 | B87: =B86+1 -> 15 | C87: =VLOOKUP(B87,'[1]Bo phan'!$B$5:$C$25,2,0) -> Bộ phận Logistic - Giao nhận | D87: =A87&B87 -> 5015 | E87: ="HNO."&C87 -> HNO.Bộ phận Logistic - Giao nhận | G87: 2
A88: =$A$82 -> 50 | B88: =B87+1 -> 16 | C88: =VLOOKUP(B88,'[1]Bo phan'!$B$5:$C$25,2,0) -> Bộ phận Marketing | D88: =A88&B88 -> 5016 | E88: ="HNO."&C88 -> HNO.Bộ phận Marketing | G88: 2
A89: =$A$82 -> 50 | B89: =B88+1 -> 17 | C89: =VLOOKUP(B89,'[1]Bo phan'!$B$5:$C$25,2,0) -> Bộ phận Trade Marketing | D89: =A89&B89 -> 5017 | E89: ="HNO."&C89 -> HNO.Bộ phận Trade Marketing | G89: 2
A90: =$A$82 -> 50 | B90: =B89+1 -> 18 | C90: =VLOOKUP(B90,'[1]Bo phan'!$B$5:$C$25,2,0) -> Bộ phận Tài chính - Kế toán | D90: =A90&B90 -> 5018 | E90: ="HNO."&C90 -> HNO.Bộ phận Tài chính - Kế toán | G90: 2
A91: =$A$82 -> 50 | B91: =B90+1 -> 19 | C91: =VLOOKUP(B91,'[1]Bo phan'!$B$5:$C$25,2,0) -> Bộ phận Hành chính - Nhân sự | D91: =A91&B91 -> 5019 | E91: ="HNO."&C91 -> HNO.Bộ phận Hành chính - Nhân sự | G91: 2
A92: =$A$82 -> 50 | B92: =B91+1 -> 20 | C92: =VLOOKUP(B92,'[1]Bo phan'!$B$5:$C$25,2,0) -> Bộ phận Kế hoạch | D92: =A92&B92 -> 5020 | E92: ="HNO."&C92 -> HNO.Bộ phận Kế hoạch | G92: 2
A93: =$A$82 -> 50 | B93: =B92+1 -> 21 | C93: =VLOOKUP(B93,'[1]Bo phan'!$B$5:$C$25,2,0) -> Bộ phận Xuất nhập khẩu | D93: =A93&B93 -> 5021 | E93: ="HNO."&C93 -> HNO.Bộ phận Xuất nhập khẩu | G93: 2
A94: =$A$82 -> 50 | B94: =B93+1 -> 22 | C94: =VLOOKUP(B94,'[1]Bo phan'!$B$5:$C$25,2,0) -> Bộ phận Sourcing | D94: =A94&B94 -> 5022 | E94: ="HNO."&C94 -> HNO.Bộ phận Sourcing | G94: 2
A95: =$A$82 -> 50 | B95: =B94+1 -> 23 | C95: =VLOOKUP(B95,'[1]Bo phan'!$B$5:$C$25,2,0) -> Bộ phận Mua hàng | D95: =A95&B95 -> 5023 | E95: ="HNO."&C95 -> HNO.Bộ phận Mua hàng | G95: 2
... A100: =$A$82 -> 50 | B100: =B99+1 -> 28 | C100: =VLOOKUP(B100,'[1]Bo phan'!$B$5:$C$25,2,0) -> Bộ phận chung | D100: =A100&B100 -> 5028 | E100: ="HNO."&C100 -> HNO.Bộ phận chung | G100: 2
A101: 60 | D101: 6000 | E101: CẦN THƠ | F101: x | G101: 1
A102: =$A$101 -> 60 | B102: 11 | C102: =VLOOKUP(B102,'[1]Bo phan'!$B$5:$C$25,2,0) -> Bộ phận Ban Điều hành | D102: =A102&B102 -> 6011 | E102: ="CTH."&C102 -> CTH.Bộ phận Ban Điều hành | G102: 2
A103: =$A$101 -> 60 | B103: =B102+1 -> 12 | C103: =VLOOKUP(B103,'[1]Bo phan'!$B$5:$C$25,2,0) -> Bộ phận Kinh doanh | D103: =D102+1 -> 6012 | E103: ="CTH."&C103 -> CTH.Bộ phận Kinh doanh | G103: 2
A104: =$A$101 -> 60 | B104: =B103+1 -> 13 | C104: =VLOOKUP(B104,'[1]Bo phan'!$B$5:$C$25,2,0) -> Bộ phận Logistic - Quản lý | D104: =D103+1 -> 6013 | E104: ="CTH."&C104 -> CTH.Bộ phận Logistic - Quản lý | G104: 2
A105: =$A$101 -> 60 | B105: =B104+1 -> 14 | C105: =VLOOKUP(B105,'[1]Bo phan'!$B$5:$C$25,2,0) -> Bộ phận Logistic - Kho | D105: =D104+1 -> 6014 | E105: ="CTH."&C105 -> CTH.Bộ phận Logistic - Kho | G105: 2
A106: =$A$101 -> 60 | B106: =B105+1 -> 15 | C106: =VLOOKUP(B106,'[1]Bo phan'!$B$5:$C$25,2,0) -> Bộ phận Logistic - Giao nhận | D106: =D105+1 -> 6015 | E106: ="CTH."&C106 -> CTH.Bộ phận Logistic - Giao nhận | G106: 2
A107: =$A$101 -> 60 | B107: =B106+1 -> 16 | C107: =VLOOKUP(B107,'[1]Bo phan'!$B$5:$C$25,2,0) -> Bộ phận Marketing | D107: =D106+1 -> 6016 | E107: ="CTH."&C107 -> CTH.Bộ phận Marketing | G107: 2
A108: =$A$101 -> 60 | B108: =B107+1 -> 17 | C108: =VLOOKUP(B108,'[1]Bo phan'!$B$5:$C$25,2,0) -> Bộ phận Trade Marketing | D108: =D107+1 -> 6017 | E108: ="CTH."&C108 -> CTH.Bộ phận Trade Marketing | G108: 2
A109: =$A$101 -> 60 | B109: =B108+1 -> 18 | C109: =VLOOKUP(B109,'[1]Bo phan'!$B$5:$C$25,2,0) -> Bộ phận Tài chính - Kế toán | D109: =D108+1 -> 6018 | E109: ="CTH."&C109 -> CTH.Bộ phận Tài chính - Kế toán | G109: 2
A110: =$A$101 -> 60 | B110: =B109+1 -> 19 | C110: =VLOOKUP(B110,'[1]Bo phan'!$B$5:$C$25,2,0) -> Bộ phận Hành chính - Nhân sự | D110: =D109+1 -> 6019 | E110: ="CTH."&C110 -> CTH.Bộ phận Hành chính - Nhân sự | G110: 2
A111: =$A$101 -> 60 | B111: =B110+1 -> 20 | C111: =VLOOKUP(B111,'[1]Bo phan'!$B$5:$C$25,2,0) -> Bộ phận Kế hoạch | D111: =D110+1 -> 6020 | E111: ="CTH."&C111 -> CTH.Bộ phận Kế hoạch | G111: 2
A112: =$A$101 -> 60 | B112: =B111+1 -> 21 | C112: =VLOOKUP(B112,'[1]Bo phan'!$B$5:$C$25,2,0) -> Bộ phận Xuất nhập khẩu | D112: =D111+1 -> 6021 | E112: ="CTH."&C112 -> CTH.Bộ phận Xuất nhập khẩu | G112: 2
A113: =$A$101 -> 60 | B113: =B112+1 -> 22 | C113: =VLOOKUP(B113,'[1]Bo phan'!$B$5:$C$25,2,0) -> Bộ phận Sourcing | D113: =D112+1 -> 6022 | E113: ="CTH."&C113 -> CTH.Bộ phận Sourcing | G113: 2
A114: =$A$101 -> 60 | B114: =B113+1 -> 23 | C114: =VLOOKUP(B114,'[1]Bo phan'!$B$5:$C$25,2,0) -> Bộ phận Mua hàng | D114: =D113+1 -> 6023 | E114: ="CTH."&C114 -> CTH.Bộ phận Mua hàng | G114: 2
... A119: =$A$101 -> 60 | B119: =B118+1 -> 28 | C119: =VLOOKUP(B119,'[1]Bo phan'!$B$5:$C$25,2,0) -> Bộ phận chung | D119: =D118+1 -> 6028 | E119: ="CTH."&C119 -> CTH.Bộ phận chung | G119: 2

Sheet Bank R
A1: Viết tắt | B1: Bank | C1: Branch | D1: Cost center | E1: Account | H1: 62000 | I1: Chi phí bao bì, vật tư
A2: Vietinbank | B2: NGÂN HÀNG TMCP CÔNG THƯƠNG VN | C2: CN KHANH HOA | D2: Nha Trang | E2: 110002918467 | F2: VND | H2: 63000 | I2: Chi phí công cụ, dụng cụ, đồ dùng
H3: 64000 | I3: Chi phí khấu hao
A4: VCB | B4: NGÂN HÀNG NGOẠI THƯƠNG VN | C4: CN HOANG VAN THU | D4: HCM | E4: 1024910750 | F4: VND | H4: 65000 | I4: Chi phí thuế, phí
C5: CN KHANH HOA | D5: Nha Trang | E5: 1025805620 | F5: VND | H5: 66000 | I5: Chi phí hỗ trợ bán hàng
C6: CN DA NANG | D6: Đà Nẵng | E6: 1025853063 | F6: VND | H6: 67100 | I6: Chi phí vận chuyển
C7: CN Dak Lak | D7: Dak Lak | E7: 1025916693 | F7: VND | H7: 67200 | I7: Chi phí thuê kho
C8: CN HA NOI | D8: Hà Nội | E8: 1026160515 | F8: VND | H8: 67300 | I8: Chi phí dịch vụ mua ngoài
C9: CN KHANH HOA | D9: Nha Trang | E9: 1027287004 | F9: USD | H9: 68000 | I9: Chi phí khác
A10: MB | B10: NGÂN HÀNG TMCP QUÂN ĐỘI
A11: BIDV | B11: NGÂN HÀNG TMCP ĐẦU TƯ & PHÁT TRIỂN VN
A12: ACB | B12: NGÂN HÀNG TMCP Á CHÂU
A13: TCB | B13: NGÂN HÀNG TMCP KỸ THƯƠNG VN
A14: ABBANK | B14: NGÂN HÀNG TM CP AN BÌNH
A15: MSB | B15: NGÂN HÀNG TM CP HÀNG HẢI VIỆT NAM
A16: BVB | B16: NGÂN HÀNG TMCP BẢO VIỆT
A17: Vietinbank | B17: NGÂN HÀNG TMCP CÔNG THƯƠNG
A18: SeABank | B18: NGÂN HÀNG TMCP ĐÔNG NAM Á ( SEABANK)
A19: NamA Bank | B19: NGÂN HÀNG TMCP NAM Á
A20: VDB | B20: NGÂN HÀNG TMCP PHÁT TRIỂN TP.HCM
A21: OCB | B21: NGÂN HÀNG TMCP PHƯƠNG ĐÔNG
... A28: HSBC | B28: NGÂN HÀNG TNHH MTV HSBC

Sheet Bo phan
A2: DANH MỤC BỘ PHẬN QUẢN LÝ
C5: Tên Khối/ Bộ phận/ Site | D5: Ghi chú
B6: 1 | C6: Khối trực tiếp
B7: 2 | C7: Khối gián tiếp
C11: Bộ phận Ban Điều hành
C12: Bộ phận Kinh doanh
C13: Bộ phận Logistic - Quản lý
C14: Bộ phận Logistic - Kho
C15: Bộ phận Logistic - Giao nhận | D15: Hiện nay đang theo dõi chi tiết theo từng xe tải
C16: Bộ phận Marketing
C17: Bộ phận Trade Marketing
C18: Bộ phận Tài chính - Kế toán
C19: Bộ phận Hành chính - Nhân sự
C20: Bộ phận Kế hoạch
C21: Bộ phận Xuất nhập khẩu
C22: Bộ phận Sourcing
C23: Bộ phận Mua hàng
C24: Bộ phận Công nghệ thông tin
C25: Bộ phận Nghiên cứu phát triển
C26: Bộ phận Bảo trì - Kỹ thuật - Cơ điện
C27: Bộ phận QA-QC-ATTP-LAB
C28: Bộ phận chung
B31: Mã Site | C31: Tên site | D31: Ký hiệu
B32: 10 | C32: Hồ Chí Minh | D32: HCM
B33: 20 | C33: Nha Trang | D33: NTR
B34: 30 | C34: Đắc Lắc | D34: DLA
B35: 40 | C35: Đà Nẵng | D35: DNG
B36: 50 | C36: Hà Nội | D36: HNO
B37: 60 | C37: Cần Thơ | D37: CTH
B46: Mã Bộ phận | C46: Tên bộ phận hiện tại
B47: 1000 | C47: Bộ phận Ban Điều hành
B48: 1001 | C48: Bộ phận Kinh doanh Trực tiếp
B49: 1002 | C49: Bộ phận Kinh doanh Gián tiếp
B50: 1003 | C50: Bộ phận Marketing
B51: 1004 | C51: Bộ phận Trade Marketing
B52: 1005 | C52: Bộ phận Tài chính - Kế toán
B53: 1006 | C53: Bộ phận Hành chính - Nhân sự
B54: 1007 | C54: Bộ phận Kế hoạch
B55: 1008 | C55: Bộ phận Xuất nhập khẩu
B56: 1009 | C56: Bộ phận Sourcing - Mua hàng
B57: 1010 | C57: Bộ phận Công nghệ thông tin
B58: 1011 | C58: Bộ phận Nghiên cứu phát triển
... B64: 1102 | C64: Logistic - Giao nhận
